{"version": 0.6, "generator": "Overpass API 0.7.62.10 2d4cfc48", "osm3s": {"timestamp_osm_base": "2026-02-17T11:48:30Z", "copyright": "The data included in this document is from www.openstreetmap.org. The data is made available under ODbL."}, "elements": [{"type": "node", "id": 277192950, "lat": 56.6565746, "lon": 8.4966746}, {"type": "node", "id": 277192951, "lat": 56.656496, "lon": 8.5029668}, {"type": "node", "id": 277192952, "lat": 56.6548704, "lon": 8.5115501}, {"type": "node", "id": 277192953, "lat": 56.6528992, "lon": 8.5174347}, {"type": "node", "id": 277192990, "lat": 56.656722, "lon": 8.4789117}, {"type": "node", "id": 277192991, "lat": 56.6568326, "lon": 8.4769107}, {"type": "node", "id": 277192992, "lat": 56.6576136, "lon": 8.4725616}, {"type": "node", "id": 277192994, "lat": 56.6592706, "lon": 8.4678155}, {"type": "node", "id": 277192995, "lat": 56.6623389, "lon": 8.4599205}, {"type": "node", "id": 277192996, "lat": 56.6634111, "lon": 8.4570531}, {"type": "node", "id": 277192997, "lat": 56.664082, "lon": 8.4536408}, {"type": "node", "id": 277192998, "lat": 56.6650159, "lon": 8.4434709}, {"type": "node", "id": 277192999, "lat": 56.6661693, "lon": 8.4306288}, {"type": "node", "id": 277193325, "lat": 56.6670346, "lon": 8.4217998}, {"type": "node", "id": 277193326, "lat": 56.6675806, "lon": 8.4188303}, {"type": "node", "id": 277193327, "lat": 56.6696636, "lon": 8.4097106}, {"type": "node", "id": 277193328, "lat": 56.6712416, "lon": 8.4053195}, {"type": "node", "id": 277193329, "lat": 56.67356, "lon": 8.4022378}, {"type": "node", "id": 277193330, "lat": 56.6768436, "lon": 8.39866}, {"type": "node", "id": 277193331, "lat": 56.6820337, "lon": 8.3946272}, {"type": "node", "id": 277193433, "lat": 56.6985095, "lon": 8.4034131}, {"type": "node", "id": 277193434, "lat": 56.6970681, "lon": 8.401533}, {"type": "node", "id": 277193435, "lat": 56.6933691, "lon": 8.3966745}, {"type": "node", "id": 277193436, "lat": 56.691798, "lon": 8.3959682}, {"type": "node", "id": 277193437, "lat": 56.6906299, "lon": 8.3961843}, {"type": "node", "id": 277193438, "lat": 56.6892002, "lon": 8.3968794}, {"type": "node", "id": 277193439, "lat": 56.6876593, "lon": 8.3966136}, {"type": "node", "id": 277193441, "lat": 56.6835278, "lon": 8.3943079}, {"type": "node", "id": 277193442, "lat": 56.6828649, "lon": 8.3942926}, {"type": "node", "id": 277193666, "lat": 56.7004675, "lon": 8.4044849}, {"type": "node", "id": 277193667, "lat": 56.7022845, "lon": 8.4041794}, {"type": "node", "id": 277193668, "lat": 56.7041795, "lon": 8.4036758}, {"type": "node", "id": 277193669, "lat": 56.7057118, "lon": 8.4030963}, {"type": "node", "id": 277193670, "lat": 56.7067461, "lon": 8.4022463}, {"type": "node", "id": 277193671, "lat": 56.7097991, "lon": 8.3992068}, {"type": "node", "id": 277193672, "lat": 56.7125815, "lon": 8.398206}, {"type": "node", "id": 277193673, "lat": 56.7137658, "lon": 8.3985617, "tags": {"crossing:barrier": "half", "crossing:bell": "yes", "crossing:light": "yes", "railway": "level_crossing", "railway:position": "35.1", "ref": "90"}}, {"type": "node", "id": 277193936, "lat": 56.7173955, "lon": 8.3998272}, {"type": "node", "id": 277193937, "lat": 56.7188119, "lon": 8.4007557}, {"type": "node", "id": 277193938, "lat": 56.7205766, "lon": 8.4046961}, {"type": "node", "id": 277193939, "lat": 56.7219327, "lon": 8.4072852}, {"type": "node", "id": 277194373, "lat": 56.7454707, "lon": 8.417509}, {"type": "node", "id": 277194422, "lat": 56.7306814, "lon": 8.4127562}, {"type": "node", "id": 277194529, "lat": 56.7784155, "lon": 8.3992183}, {"type": "node", "id": 277194530, "lat": 56.7779776, "lon": 8.3996942}, {"type": "node", "id": 277194531, "lat": 56.7753037, "lon": 8.4030854}, {"type": "node", "id": 277194532, "lat": 56.7718523, "lon": 8.4082251}, {"type": "node", "id": 277194534, "lat": 56.7662515, "lon": 8.4185873}, {"type": "node", "id": 277194535, "lat": 56.7632983, "lon": 8.4211465}, {"type": "node", "id": 277194539, "lat": 56.7321472, "lon": 8.4127232}, {"type": "node", "id": 277194540, "lat": 56.733816, "lon": 8.4122332}, {"type": "node", "id": 277194542, "lat": 56.7352904, "lon": 8.4119615}, {"type": "node", "id": 277194543, "lat": 56.7378282, "lon": 8.4128376}, {"type": "node", "id": 277194899, "lat": 56.7616452, "lon": 8.4211336}, {"type": "node", "id": 277194900, "lat": 56.7596205, "lon": 8.4205496}, {"type": "node", "id": 277194901, "lat": 56.7564355, "lon": 8.4195855}, {"type": "node", "id": 277194902, "lat": 56.749127, "lon": 8.4174477}, {"type": "node", "id": 277194903, "lat": 56.7482826, "lon": 8.4174273}, {"type": "node", "id": 277194904, "lat": 56.7472769, "lon": 8.4175578}, {"type": "node", "id": 277194905, "lat": 56.7463925, "lon": 8.417641}, {"type": "node", "id": 277195416, "lat": 56.7870491, "lon": 8.3967198}, {"type": "node", "id": 278787353, "lat": 56.7599722, "lon": 8.4206527}, {"type": "node", "id": 281923536, "lat": 56.8410191, "lon": 8.4830271}, {"type": "node", "id": 281923541, "lat": 56.8243747, "lon": 8.4566848}, {"type": "node", "id": 281923544, "lat": 56.817782, "lon": 8.4331539}, {"type": "node", "id": 281923545, "lat": 56.8164533, "lon": 8.4302406}, {"type": "node", "id": 281923664, "lat": 56.8662234, "lon": 8.5170808}, {"type": "node", "id": 281923665, "lat": 56.8648944, "lon": 8.5151402}, {"type": "node", "id": 281923666, "lat": 56.8549301, "lon": 8.4944798}, {"type": "node", "id": 281923667, "lat": 56.8534686, "lon": 8.4925128}, {"type": "node", "id": 281923668, "lat": 56.8401638, "lon": 8.4821045}, {"type": "node", "id": 281923669, "lat": 56.8360476, "lon": 8.4714923}, {"type": "node", "id": 281923671, "lat": 56.8291639, "lon": 8.4638885, "tags": {"crossing:barrier": "yes", "crossing:bell": "yes", "crossing:light": "yes", "railway": "level_crossing", "railway:position": "50.8", "ref": "154"}}, {"type": "node", "id": 322717135, "lat": 56.8469034, "lon": 8.4875093, "tags": {"crossing:barrier": "yes", "crossing:bell": "yes", "crossing:light": "yes", "railway": "level_crossing", "railway:position": "53.3", "ref": "165"}}, {"type": "node", "id": 325274746, "lat": 56.8097582, "lon": 8.4204751}, {"type": "node", "id": 325278717, "lat": 56.7297914, "lon": 8.4124266}, {"type": "node", "id": 325278718, "lat": 56.7303153, "lon": 8.4126537}, {"type": "node", "id": 325278719, "lat": 56.7311495, "lon": 8.4128259}, {"type": "node", "id": 325278720, "lat": 56.7316199, "lon": 8.4128154}, {"type": "node", "id": 325278721, "lat": 56.7328488, "lon": 8.412528}, {"type": "node", "id": 325278722, "lat": 56.7343624, "lon": 8.4120703}, {"type": "node", "id": 325278723, "lat": 56.7360152, "lon": 8.4120273}, {"type": "node", "id": 325278724, "lat": 56.7364249, "lon": 8.4121246}, {"type": "node", "id": 325278725, "lat": 56.736834, "lon": 8.4122772}, {"type": "node", "id": 499503593, "lat": 56.7056865, "lon": 8.2190998, "tags": {"railway": "buffer_stop"}}, {"type": "node", "id": 499503595, "lat": 56.7022151, "lon": 8.2098455}, {"type": "node", "id": 499503597, "lat": 56.7015264, "lon": 8.2087079}, {"type": "node", "id": 499503602, "lat": 56.6996839, "lon": 8.2071884}, {"type": "node", "id": 499503604, "lat": 56.6988696, "lon": 8.2069206}, {"type": "node", "id": 499503609, "lat": 56.6964569, "lon": 8.2073641}, {"type": "node", "id": 499503612, "lat": 56.6937377, "lon": 8.2082264}, {"type": "node", "id": 499503614, "lat": 56.6930511, "lon": 8.208718}, {"type": "node", "id": 499503616, "lat": 56.6922108, "lon": 8.2096925, "tags": {"name": "Sprog\u00f8vej", "public_transport": "stop_position", "railway": "stop", "train": "yes"}}, {"type": "node", "id": 499503617, "lat": 56.6915138, "lon": 8.2109695}, {"type": "node", "id": 499503619, "lat": 56.690807, "lon": 8.2130415}, {"type": "node", "id": 499503621, "lat": 56.68886, "lon": 8.2190837}, {"type": "node", "id": 499503623, "lat": 56.6879715, "lon": 8.2205897}, {"type": "node", "id": 499503624, "lat": 56.6873405, "lon": 8.2212621}, {"type": "node", "id": 499503626, "lat": 56.6867694, "lon": 8.2216704}, {"type": "node", "id": 499503628, "lat": 56.6850939, "lon": 8.2225762}, {"type": "node", "id": 499503629, "lat": 56.6830336, "lon": 8.2236337}, {"type": "node", "id": 499503631, "lat": 56.6818141, "lon": 8.2238415}, {"type": "node", "id": 499503634, "lat": 56.6810045, "lon": 8.2237397}, {"type": "node", "id": 499503635, "lat": 56.6799698, "lon": 8.2233309}, {"type": "node", "id": 499503638, "lat": 56.6790767, "lon": 8.2226931}, {"type": "node", "id": 499503640, "lat": 56.678043, "lon": 8.2215524}, {"type": "node", "id": 499503641, "lat": 56.6717437, "lon": 8.2120408}, {"type": "node", "id": 499503644, "lat": 56.6652787, "lon": 8.2022625}, {"type": "node", "id": 499503647, "lat": 56.6629146, "lon": 8.1987194}, {"type": "node", "id": 499503648, "lat": 56.6611907, "lon": 8.1969676}, {"type": "node", "id": 499503650, "lat": 56.6605269, "lon": 8.1965192}, {"type": "node", "id": 499503652, "lat": 56.6568684, "lon": 8.1948896, "tags": {"name": "R\u00f8nland", "public_transport": "stop_position", "railway": "stop", "train": "yes"}}, {"type": "node", "id": 499503654, "lat": 56.6390955, "lon": 8.1873283}, {"type": "node", "id": 608662604, "lat": 56.6755352, "lon": 8.399855}, {"type": "node", "id": 608662649, "lat": 56.7114437, "lon": 8.3982589}, {"type": "node", "id": 608662671, "lat": 56.6560292, "lon": 8.5074626}, {"type": "node", "id": 608662673, "lat": 56.6517786, "lon": 8.5207873}, {"type": "node", "id": 770393526, "lat": 56.850341, "lon": 8.4901249, "tags": {"crossing:barrier": "half", "crossing:bell": "yes", "crossing:light": "yes", "railway": "level_crossing", "railway:position": "53.7", "ref": "167"}}, {"type": "node", "id": 858835505, "lat": 56.6556193, "lon": 8.5092}, {"type": "node", "id": 858835508, "lat": 56.656366, "lon": 8.5051291}, {"type": "node", "id": 935036599, "lat": 56.7034199, "lon": 8.2129731, "tags": {"crossing:barrier": "half", "crossing:bell": "yes", "crossing:light": "yes", "mapillary": "477697293459178", "railway": "level_crossing", "railway:position": "28.0", "ref": "87N"}}, {"type": "node", "id": 935084469, "lat": 56.7043826, "lon": 8.215576, "tags": {"crossing:barrier": "no", "crossing:bell": "yes", "crossing:light": "yes", "crossing:saltire": "yes", "railway": "level_crossing", "ref": "88N"}}, {"type": "node", "id": 935084487, "lat": 56.7006111, "lon": 8.2078248, "tags": {"crossing:barrier": "half", "crossing:bell": "yes", "crossing:light": "yes", "railway": "level_crossing", "ref": "86N"}}, {"type": "node", "id": 935084528, "lat": 56.6985199, "lon": 8.2068826}, {"type": "node", "id": 935084536, "lat": 56.6979272, "lon": 8.2069511, "tags": {"crossing:barrier": "no", "crossing:bell": "no", "crossing:light": "no", "railway": "crossing"}}, {"type": "node", "id": 935084539, "lat": 56.6975096, "lon": 8.2070628}, {"type": "node", "id": 1149046847, "lat": 56.8380768, "lon": 8.4757221}, {"type": "node", "id": 1149046860, "lat": 56.8369221, "lon": 8.4727771}, {"type": "node", "id": 1149046861, "lat": 56.8391991, "lon": 8.4802175}, {"type": "node", "id": 1149046863, "lat": 56.8542331, "lon": 8.4933912}, {"type": "node", "id": 1149046865, "lat": 56.8378317, "lon": 8.4749014}, {"type": "node", "id": 1149046871, "lat": 56.8397207, "lon": 8.4813948}, {"type": "node", "id": 1149046890, "lat": 56.837261, "lon": 8.4734262}, {"type": "node", "id": 1165238933, "lat": 56.6943704, "lon": 8.2079726}, {"type": "node", "id": 1165238934, "lat": 56.6992077, "lon": 8.2069971}, {"type": "node", "id": 1165238963, "lat": 56.6926003, "lon": 8.209182}, {"type": "node", "id": 1165239003, "lat": 56.691169, "lon": 8.2118749}, {"type": "node", "id": 1165239010, "lat": 56.689162, "lon": 8.2183419}, {"type": "node", "id": 1165239039, "lat": 56.7018686, "lon": 8.2092137}, {"type": "node", "id": 1165239074, "lat": 56.695056, "lon": 8.2077749}, {"type": "node", "id": 1165239084, "lat": 56.6918146, "lon": 8.2103423}, {"type": "node", "id": 1165239106, "lat": 56.7010773, "lon": 8.2082041}, {"type": "node", "id": 1165239142, "lat": 56.6942045, "lon": 8.2080231}, {"type": "node", "id": 1165239153, "lat": 56.6934421, "lon": 8.2084066}, {"type": "node", "id": 1165239236, "lat": 56.701261, "lon": 8.2083834}, {"type": "node", "id": 1165239338, "lat": 56.7023912, "lon": 8.2102307}, {"type": "node", "id": 1165239352, "lat": 56.688554, "lon": 8.2196936}, {"type": "node", "id": 1165239414, "lat": 56.7042602, "lon": 8.2152417, "tags": {"railway": "switch"}}, {"type": "node", "id": 1165239431, "lat": 56.6894231, "lon": 8.217516}, {"type": "node", "id": 1165239498, "lat": 56.7026037, "lon": 8.2107605}, {"type": "node", "id": 1165239506, "lat": 56.689771, "lon": 8.2163975}, {"type": "node", "id": 1165239594, "lat": 56.6919419, "lon": 8.2101219, "tags": {"crossing:barrier": "no", "crossing:bell": "no", "crossing:light": "no", "railway": "crossing"}}, {"type": "node", "id": 1187623824, "lat": 56.7380001, "lon": 8.4129541, "tags": {"crossing:barrier": "half", "crossing:bell": "yes", "crossing:light": "yes", "railway": "level_crossing", "railway:position": "38.0", "ref": "102"}}, {"type": "node", "id": 1187624004, "lat": 56.7373456, "lon": 8.4125207}, {"type": "node", "id": 1187624115, "lat": 56.6937782, "lon": 8.3970622}, {"type": "node", "id": 1187624356, "lat": 56.7530569, "lon": 8.4185705}, {"type": "node", "id": 1187624606, "lat": 56.7519341, "lon": 8.4182355, "tags": {"crossing:barrier": "no", "crossing:bell": "no", "crossing:chicane": "yes", "crossing:light": "no", "railway": "crossing"}}, {"type": "node", "id": 1187624626, "lat": 56.7503699, "lon": 8.4177642, "tags": {"crossing:barrier": "half", "crossing:bell": "yes", "crossing:light": "yes", "railway": "level_crossing", "railway:position": "39.5", "ref": "112"}}, {"type": "node", "id": 1187624909, "lat": 56.752952, "lon": 8.4186047, "tags": {"crossing:barrier": "double_half", "crossing:bell": "yes", "crossing:light": "yes", "railway": "level_crossing", "railway:position": "39.8", "ref": "113"}}, {"type": "node", "id": 1187625093, "lat": 56.7504518, "lon": 8.4177831, "tags": {"railway": "switch", "ref": "N001"}}, {"type": "node", "id": 1187625101, "lat": 56.6926497, "lon": 8.3961898}, {"type": "node", "id": 1187625281, "lat": 56.6815867, "lon": 8.3949555, "tags": {"crossing:barrier": "full", "crossing:bell": "yes", "crossing:light": "yes", "railway": "level_crossing", "railway:position": "31.2", "ref": "72"}}, {"type": "node", "id": 1187625460, "lat": 56.7040256, "lon": 8.4037191}, {"type": "node", "id": 1187625467, "lat": 56.7529737, "lon": 8.4185438, "tags": {"crossing:barrier": "double_half", "crossing:bell": "yes", "crossing:light": "yes", "railway": "level_crossing", "railway:position": "39.8", "ref": "113"}}, {"type": "node", "id": 1187625486, "lat": 56.7519753, "lon": 8.418247}, {"type": "node", "id": 1227976517, "lat": 56.6703096, "lon": 8.407317}, {"type": "node", "id": 1227976591, "lat": 56.666868, "lon": 8.4230503, "tags": {"crossing:barrier": "half", "crossing:bell": "yes", "crossing:light": "yes", "railway": "level_crossing", "railway:position": "28.7", "ref": "68"}}, {"type": "node", "id": 1227979886, "lat": 56.6642654, "lon": 8.4517074, "tags": {"crossing:barrier": "half", "crossing:bell": "yes", "crossing:light": "yes", "railway": "level_crossing", "railway:position": "26.9", "ref": "63"}}, {"type": "node", "id": 1239634436, "lat": 56.8236783, "lon": 8.4543299, "tags": {"crossing:barrier": "yes", "crossing:bell": "yes", "crossing:light": "154", "railway": "level_crossing", "railway:position": "50.0", "ref": "151"}}, {"type": "node", "id": 1302252677, "lat": 56.6580822, "lon": 8.4710814, "tags": {"crossing:barrier": "yes", "crossing:bell": "yes", "crossing:light": "yes", "railway": "level_crossing", "railway:position": "25.5", "ref": "55"}}, {"type": "node", "id": 1302252871, "lat": 56.6565233, "lon": 8.499992, "tags": {"crossing:barrier": "half", "crossing:bell": "yes", "crossing:light": "yes", "railway": "level_crossing", "railway:position": "23.7", "ref": "45"}}, {"type": "node", "id": 1302253144, "lat": 56.6566077, "lon": 8.4918464}, {"type": "node", "id": 1402454803, "lat": 56.6245411, "lon": 8.1810561, "tags": {"crossing:barrier": "no", "crossing:bell": "no", "crossing:light": "no", "railway": "level_crossing"}}, {"type": "node", "id": 1458085940, "lat": 56.6565487, "lon": 8.1947615, "tags": {"railway": "switch"}}, {"type": "node", "id": 1458085945, "lat": 56.6568454, "lon": 8.1949712}, {"type": "node", "id": 1458085949, "lat": 56.6569862, "lon": 8.1951158}, {"type": "node", "id": 1458085956, "lat": 56.6571293, "lon": 8.1950102, "tags": {"crossing:barrier": "half", "crossing:bell": "yes", "crossing:light": "yes", "railway": "level_crossing", "ref": "85N"}}, {"type": "node", "id": 1458085957, "lat": 56.6571141, "lon": 8.1952734, "tags": {"crossing:barrier": "half", "crossing:bell": "yes", "crossing:light": "yes", "railway": "level_crossing"}}, {"type": "node", "id": 1458085963, "lat": 56.6573567, "lon": 8.1956713, "tags": {"crossing:barrier": "no", "crossing:bell": "no", "crossing:light": "no", "railway": "crossing"}}, {"type": "node", "id": 1458085965, "lat": 56.6578146, "lon": 8.1964664, "tags": {"railway": "switch"}}, {"type": "node", "id": 1458085967, "lat": 56.6579594, "lon": 8.1968361}, {"type": "node", "id": 1458085969, "lat": 56.6580453, "lon": 8.1971066}, {"type": "node", "id": 1458085970, "lat": 56.658115, "lon": 8.1974659}, {"type": "node", "id": 1458085971, "lat": 56.6581533, "lon": 8.1984963, "tags": {"railway": "switch"}}, {"type": "node", "id": 1458085972, "lat": 56.6581545, "lon": 8.1978633}, {"type": "node", "id": 1458085973, "lat": 56.6581661, "lon": 8.1982141}, {"type": "node", "id": 1458085975, "lat": 56.6582551, "lon": 8.1972217, "tags": {"railway": "switch"}}, {"type": "node", "id": 1458085977, "lat": 56.6584184, "lon": 8.19751, "tags": {"railway": "switch"}}, {"type": "node", "id": 1458085978, "lat": 56.6585743, "lon": 8.1976542}, {"type": "node", "id": 1458085980, "lat": 56.658662, "lon": 8.1981838}, {"type": "node", "id": 1458085981, "lat": 56.6586765, "lon": 8.198022}, {"type": "node", "id": 1458085982, "lat": 56.6586297, "lon": 8.201809, "tags": {"railway": "buffer_stop"}}, {"type": "node", "id": 1458085984, "lat": 56.6587433, "lon": 8.19856}, {"type": "node", "id": 1458085985, "lat": 56.6587503, "lon": 8.1999339}, {"type": "node", "id": 1458085986, "lat": 56.6587851, "lon": 8.198987}, {"type": "node", "id": 1458085987, "lat": 56.6587898, "lon": 8.1992913}, {"type": "node", "id": 1458085988, "lat": 56.6587975, "lon": 8.1978511}, {"type": "node", "id": 1458085989, "lat": 56.6588912, "lon": 8.1957572}, {"type": "node", "id": 1458085990, "lat": 56.6588949, "lon": 8.1985884}, {"type": "node", "id": 1458085992, "lat": 56.6589995, "lon": 8.1979628}, {"type": "node", "id": 1458085994, "lat": 56.6592029, "lon": 8.1980118, "tags": {"railway": "switch"}}, {"type": "node", "id": 1458085995, "lat": 56.659549, "lon": 8.1980697}, {"type": "node", "id": 1458085996, "lat": 56.6593364, "lon": 8.1997297}, {"type": "node", "id": 1458086000, "lat": 56.6597207, "lon": 8.2007492, "tags": {"railway": "switch"}}, {"type": "node", "id": 1458086004, "lat": 56.659878, "lon": 8.2011627}, {"type": "node", "id": 1458086009, "lat": 56.6599511, "lon": 8.1981404, "tags": {"railway": "buffer_stop"}}, {"type": "node", "id": 1458086010, "lat": 56.6599564, "lon": 8.1980692, "tags": {"railway": "buffer_stop"}}, {"type": "node", "id": 1458086011, "lat": 56.6599962, "lon": 8.196237}, {"type": "node", "id": 1458086012, "lat": 56.6600549, "lon": 8.2016331}, {"type": "node", "id": 1458086013, "lat": 56.6601575, "lon": 8.2018998}, {"type": "node", "id": 1458086014, "lat": 56.6601473, "lon": 8.2068987, "tags": {"railway": "switch"}}, {"type": "node", "id": 1458086016, "lat": 56.6603138, "lon": 8.2025153}, {"type": "node", "id": 1458086017, "lat": 56.6603025, "lon": 8.1963919}, {"type": "node", "id": 1458086018, "lat": 56.6603284, "lon": 8.2035721, "tags": {"railway": "switch"}}, {"type": "node", "id": 1458086019, "lat": 56.66034, "lon": 8.2027648}, {"type": "node", "id": 1458086020, "lat": 56.6603516, "lon": 8.2030733, "tags": {"railway": "switch"}}, {"type": "node", "id": 1458086024, "lat": 56.6616432, "lon": 8.1973444}, {"type": "node", "id": 1458086026, "lat": 56.6620521, "lon": 8.1977257}, {"type": "node", "id": 1458086028, "lat": 56.662504, "lon": 8.1982066}, {"type": "node", "id": 1465969461, "lat": 56.7885891, "lon": 8.3968824}, {"type": "node", "id": 1518673645, "lat": 56.6866886, "lon": 8.3960496}, {"type": "node", "id": 1529929238, "lat": 56.6574546, "lon": 8.195838, "tags": {"barrier": "gate"}}, {"type": "node", "id": 1530337679, "lat": 56.6748542, "lon": 8.2167396}, {"type": "node", "id": 1578613661, "lat": 56.7734596, "lon": 8.4056291}, {"type": "node", "id": 1583590614, "lat": 56.8272113, "lon": 8.4617248}, {"type": "node", "id": 1586181117, "lat": 56.7184143, "lon": 8.400364}, {"type": "node", "id": 1586181141, "lat": 56.7195449, "lon": 8.4018955}, {"type": "node", "id": 1586181143, "lat": 56.7209656, "lon": 8.4056793}, {"type": "node", "id": 1586181145, "lat": 56.7228483, "lon": 8.4081156}, {"type": "node", "id": 1586181210, "lat": 56.7510881, "lon": 8.4180985}, {"type": "node", "id": 1586181375, "lat": 56.7620571, "lon": 8.4212213}, {"type": "node", "id": 1586181389, "lat": 56.7641073, "lon": 8.4208171}, {"type": "node", "id": 1586181397, "lat": 56.7648804, "lon": 8.4202719}, {"type": "node", "id": 1586181477, "lat": 56.7792174, "lon": 8.398579}, {"type": "node", "id": 1586181478, "lat": 56.7797983, "lon": 8.3982613}, {"type": "node", "id": 1603932190, "lat": 56.8521991, "lon": 8.4915344}, {"type": "node", "id": 1603932208, "lat": 56.8584036, "lon": 8.5017134, "tags": {"crossing:barrier": "half", "crossing:bell": "yes", "crossing:light": "yes", "railway": "level_crossing", "railway:position": "54.9", "ref": "174"}}, {"type": "node", "id": 1603932228, "lat": 56.8602181, "lon": 8.5054495}, {"type": "node", "id": 1603932268, "lat": 56.862868, "lon": 8.5110399}, {"type": "node", "id": 1603932390, "lat": 56.8663211, "lon": 8.5172079}, {"type": "node", "id": 1603932423, "lat": 56.8678897, "lon": 8.5188201}, {"type": "node", "id": 1603932425, "lat": 56.8687494, "lon": 8.5194717}, {"type": "node", "id": 1609983388, "lat": 56.7881512, "lon": 8.3967473}, {"type": "node", "id": 1609983394, "lat": 56.7895402, "lon": 8.3973702}, {"type": "node", "id": 1609983395, "lat": 56.78999, "lon": 8.3977341}, {"type": "node", "id": 1609983396, "lat": 56.7905395, "lon": 8.3983157}, {"type": "node", "id": 1609983397, "lat": 56.7929684, "lon": 8.4017445}, {"type": "node", "id": 1609983398, "lat": 56.7935209, "lon": 8.402406}, {"type": "node", "id": 1609983399, "lat": 56.7941775, "lon": 8.4030013}, {"type": "node", "id": 1609983400, "lat": 56.7949816, "lon": 8.4035725}, {"type": "node", "id": 1609983402, "lat": 56.7955619, "lon": 8.4036994}, {"type": "node", "id": 1609983409, "lat": 56.8026814, "lon": 8.4040876}, {"type": "node", "id": 1609983412, "lat": 56.803389, "lon": 8.4042526}, {"type": "node", "id": 1609983413, "lat": 56.804024, "lon": 8.404546}, {"type": "node", "id": 1609983414, "lat": 56.8045703, "lon": 8.4049176}, {"type": "node", "id": 1609983416, "lat": 56.8052953, "lon": 8.4056136}, {"type": "node", "id": 1609983417, "lat": 56.8058853, "lon": 8.4063888, "tags": {"railway": "switch", "railway:position:exact": "46.26", "ref": "N001"}}, {"type": "node", "id": 1609983425, "lat": 56.8073188, "lon": 8.4096021, "tags": {"railway": "switch", "railway:position:exact": "46.52", "ref": "N002"}}, {"type": "node", "id": 1609983431, "lat": 56.8075744, "lon": 8.4106228}, {"type": "node", "id": 1609983435, "lat": 56.8087864, "lon": 8.4174184}, {"type": "node", "id": 1609983438, "lat": 56.8089842, "lon": 8.4182705}, {"type": "node", "id": 1609983441, "lat": 56.8094474, "lon": 8.4197721}, {"type": "node", "id": 1609983447, "lat": 56.8103576, "lon": 8.4216106}, {"type": "node", "id": 1609983460, "lat": 56.8170293, "lon": 8.4312294}, {"type": "node", "id": 1609983462, "lat": 56.8174341, "lon": 8.4321462}, {"type": "node", "id": 1609983471, "lat": 56.8249503, "lon": 8.4581531}, {"type": "node", "id": 1609983473, "lat": 56.8256609, "lon": 8.4595784}, {"type": "node", "id": 1837614484, "lat": 56.6884168, "lon": 8.3968933}, {"type": "node", "id": 1837614527, "lat": 56.6888016, "lon": 8.3969265}, {"type": "node", "id": 1837614884, "lat": 56.6896321, "lon": 8.3967188}, {"type": "node", "id": 1882173155, "lat": 56.7656004, "lon": 8.4195231}, {"type": "node", "id": 1896162067, "lat": 56.8155096, "lon": 8.4288769}, {"type": "node", "id": 1906788141, "lat": 56.8060468, "lon": 8.4066934, "tags": {"crossing:barrier": "double_half", "crossing:bell": "yes", "crossing:light": "yes", "railway": "level_crossing", "railway:position": "46.3", "ref": "135"}}, {"type": "node", "id": 1974924290, "lat": 56.6569623, "lon": 8.4758647}, {"type": "node", "id": 1974924291, "lat": 56.6565702, "lon": 8.4945748}, {"type": "node", "id": 1974931686, "lat": 56.6639438, "lon": 8.4549769}, {"type": "node", "id": 1974931689, "lat": 56.6613097, "lon": 8.4626151}, {"type": "node", "id": 1974931692, "lat": 56.6572155, "lon": 8.474274}, {"type": "node", "id": 2211757253, "lat": 56.7533501, "lon": 8.4186582, "tags": {"railway": "switch", "railway:position:exact": "39.75", "ref": "N002"}}, {"type": "node", "id": 2371627104, "lat": 56.7052557, "lon": 8.2179369, "tags": {"crossing:barrier": "no", "crossing:bell": "no", "crossing:light": "no", "railway": "crossing"}}, {"type": "node", "id": 2427958680, "lat": 56.7710565, "lon": 8.4096707, "tags": {"crossing:barrier": "yes", "crossing:bell": "yes", "crossing:light": "yes", "railway": "level_crossing", "railway:position": "42.0", "ref": "121"}}, {"type": "node", "id": 2427958684, "lat": 56.7722507, "lon": 8.4075469}, {"type": "node", "id": 2427958686, "lat": 56.7740154, "lon": 8.4048242}, {"type": "node", "id": 2427958692, "lat": 56.7788202, "lon": 8.3988538}, {"type": "node", "id": 2427958699, "lat": 56.7803119, "lon": 8.398084}, {"type": "node", "id": 2427958705, "lat": 56.7876319, "lon": 8.3966674}, {"type": "node", "id": 2427958710, "lat": 56.7891114, "lon": 8.3970946}, {"type": "node", "id": 2427958712, "lat": 56.790932, "lon": 8.3988228}, {"type": "node", "id": 2427958732, "lat": 56.7964789, "lon": 8.4037844}, {"type": "node", "id": 2427958752, "lat": 56.8176232, "lon": 8.4326468}, {"type": "node", "id": 2427958756, "lat": 56.8183099, "lon": 8.4350519, "tags": {"crossing:barrier": "yes", "crossing:bell": "yes", "crossing:light": "yes", "railway": "level_crossing", "railway:position": "48.6", "ref": "144"}}, {"type": "node", "id": 2427958772, "lat": 56.822127, "lon": 8.4487456, "tags": {"crossing:barrier": "yes", "crossing:bell": "yes", "crossing:light": "yes", "railway": "level_crossing", "railway:position": "49.5", "ref": "148"}}, {"type": "node", "id": 2427958775, "lat": 56.8241307, "lon": 8.4559131}, {"type": "node", "id": 2427958778, "lat": 56.8246242, "lon": 8.4573649}, {"type": "node", "id": 2427958780, "lat": 56.8252717, "lon": 8.4588442}, {"type": "node", "id": 2427958782, "lat": 56.8260831, "lon": 8.4602695}, {"type": "node", "id": 2427958785, "lat": 56.8266094, "lon": 8.4610124}, {"type": "node", "id": 2628292672, "lat": 56.6584914, "lon": 8.1975541, "tags": {"railway": "switch"}}, {"type": "node", "id": 2628292674, "lat": 56.6585127, "lon": 8.1977243}, {"type": "node", "id": 2628292675, "lat": 56.6585485, "lon": 8.1977394}, {"type": "node", "id": 2628292677, "lat": 56.6585891, "lon": 8.2017907, "tags": {"railway": "buffer_stop"}}, {"type": "node", "id": 2628292680, "lat": 56.6585911, "lon": 8.1979396}, {"type": "node", "id": 2628292682, "lat": 56.6586186, "lon": 8.1978796}, {"type": "node", "id": 2628292684, "lat": 56.6586377, "lon": 8.2010065}, {"type": "node", "id": 2628292685, "lat": 56.6586582, "lon": 8.2007746}, {"type": "node", "id": 2628292687, "lat": 56.6587369, "lon": 8.2001424, "tags": {"railway": "switch"}}, {"type": "node", "id": 2628292690, "lat": 56.6588072, "lon": 8.1980147}, {"type": "node", "id": 2628292692, "lat": 56.6589283, "lon": 8.1982326}, {"type": "node", "id": 2628292694, "lat": 56.6590177, "lon": 8.1984203}, {"type": "node", "id": 2628292696, "lat": 56.6591154, "lon": 8.1986757}, {"type": "node", "id": 2628292698, "lat": 56.6591746, "lon": 8.198866}, {"type": "node", "id": 2628292699, "lat": 56.6595811, "lon": 8.2002976}, {"type": "node", "id": 2628292701, "lat": 56.6598259, "lon": 8.2128423, "tags": {"railway": "buffer_stop"}}, {"type": "node", "id": 2628292704, "lat": 56.6598454, "lon": 8.210417}, {"type": "node", "id": 2628292705, "lat": 56.6598493, "lon": 8.210934, "tags": {"railway": "switch"}}, {"type": "node", "id": 2628292706, "lat": 56.6598495, "lon": 8.2101466}, {"type": "node", "id": 2628292707, "lat": 56.6598512, "lon": 8.2115819, "tags": {"railway": "switch"}}, {"type": "node", "id": 2628292709, "lat": 56.6598586, "lon": 8.2122368, "tags": {"railway": "switch"}}, {"type": "node", "id": 2628292710, "lat": 56.6598743, "lon": 8.2096334}, {"type": "node", "id": 2628292712, "lat": 56.6598921, "lon": 8.2094181}, {"type": "node", "id": 2628292714, "lat": 56.6599651, "lon": 8.2087722, "tags": {"railway": "switch"}}, {"type": "node", "id": 2628292715, "lat": 56.6600421, "lon": 8.2081212, "tags": {"railway": "switch"}}, {"type": "node", "id": 2628292717, "lat": 56.6601156, "lon": 8.2074854, "tags": {"railway": "switch"}}, {"type": "node", "id": 2628292719, "lat": 56.6602036, "lon": 8.2063921}, {"type": "node", "id": 2628292721, "lat": 56.6602367, "lon": 8.2059974}, {"type": "node", "id": 2628292724, "lat": 56.660331, "lon": 8.2043014}, {"type": "node", "id": 2628292726, "lat": 56.660333, "lon": 8.203958}, {"type": "node", "id": 2628292728, "lat": 56.6604373, "lon": 8.2015115, "tags": {"railway": "buffer_stop"}}, {"type": "node", "id": 2628606438, "lat": 56.6579978, "lon": 8.20101, "tags": {"railway": "level_crossing"}}, {"type": "node", "id": 2628606479, "lat": 56.6594943, "lon": 8.2001485, "tags": {"railway": "level_crossing"}}, {"type": "node", "id": 2628606481, "lat": 56.6595008, "lon": 8.2000147, "tags": {"railway": "level_crossing"}}, {"type": "node", "id": 2628606520, "lat": 56.6601346, "lon": 8.2071328, "tags": {"railway": "level_crossing"}}, {"type": "node", "id": 2628606526, "lat": 56.6602015, "lon": 8.2059025, "tags": {"railway": "level_crossing"}}, {"type": "node", "id": 2628606530, "lat": 56.6602415, "lon": 8.2059107, "tags": {"railway": "level_crossing"}}, {"type": "node", "id": 2628606533, "lat": 56.6602695, "lon": 8.2022899, "tags": {"railway": "level_crossing"}}, {"type": "node", "id": 2628606536, "lat": 56.6603003, "lon": 8.2040883, "tags": {"railway": "level_crossing"}}, {"type": "node", "id": 2628606544, "lat": 56.6603322, "lon": 8.2040945, "tags": {"railway": "level_crossing"}}, {"type": "node", "id": 2838660840, "lat": 56.688032, "lon": 8.3967853}, {"type": "node", "id": 2838660841, "lat": 56.6910056, "lon": 8.3960485}, {"type": "node", "id": 2838660842, "lat": 56.6913737, "lon": 8.3959793}, {"type": "node", "id": 2838660843, "lat": 56.69223, "lon": 8.3960513}, {"type": "node", "id": 2838660844, "lat": 56.6930437, "lon": 8.3964363}, {"type": "node", "id": 2838660845, "lat": 56.6941661, "lon": 8.3975386}, {"type": "node", "id": 2838660846, "lat": 56.6988499, "lon": 8.4037475}, {"type": "node", "id": 2838660847, "lat": 56.6992395, "lon": 8.4040384}, {"type": "node", "id": 2838660848, "lat": 56.6996374, "lon": 8.4042773}, {"type": "node", "id": 2838660849, "lat": 56.7000395, "lon": 8.4044261}, {"type": "node", "id": 2838660850, "lat": 56.7009363, "lon": 8.404477}, {"type": "node", "id": 2838660851, "lat": 56.7048916, "lon": 8.403484}, {"type": "node", "id": 2838660852, "lat": 56.7053012, "lon": 8.4033156}, {"type": "node", "id": 2838660853, "lat": 56.7060193, "lon": 8.4028808}, {"type": "node", "id": 2838660856, "lat": 56.710272, "lon": 8.3988268}, {"type": "node", "id": 2838660857, "lat": 56.7106483, "lon": 8.3985683}, {"type": "node", "id": 2838660858, "lat": 56.7109987, "lon": 8.398392}, {"type": "node", "id": 2838660859, "lat": 56.7118823, "lon": 8.3981766}, {"type": "node", "id": 2838660860, "lat": 56.7130173, "lon": 8.3982902}, {"type": "node", "id": 2838660869, "lat": 56.7179823, "lon": 8.400082}, {"type": "node", "id": 2838660872, "lat": 56.7192074, "lon": 8.4012806}, {"type": "node", "id": 2838660874, "lat": 56.7198909, "lon": 8.4027142}, {"type": "node", "id": 2838660880, "lat": 56.7214105, "lon": 8.4065606}, {"type": "node", "id": 2838660881, "lat": 56.7223712, "lon": 8.4077317}, {"type": "node", "id": 2838660896, "lat": 56.7446187, "lon": 8.4171216}, {"type": "node", "id": 2838660897, "lat": 56.7450482, "lon": 8.4173541}, {"type": "node", "id": 2838660899, "lat": 56.7458979, "lon": 8.4175908}, {"type": "node", "id": 2838661391, "lat": 56.7542469, "lon": 8.4189261, "tags": {"crossing:barrier": "no", "crossing:bell": "no", "crossing:light": "no", "railway": "crossing"}}, {"type": "node", "id": 3020386173, "lat": 56.6665391, "lon": 8.4265432}, {"type": "node", "id": 3020386174, "lat": 56.666549, "lon": 8.4264282}, {"type": "node", "id": 3567225582, "lat": 56.8049344, "lon": 8.4052333}, {"type": "node", "id": 3567225583, "lat": 56.8051145, "lon": 8.4054128}, {"type": "node", "id": 3567225584, "lat": 56.8055861, "lon": 8.4059618}, {"type": "node", "id": 3567225585, "lat": 56.8057352, "lon": 8.406171}, {"type": "node", "id": 3567225587, "lat": 56.8068835, "lon": 8.4084965}, {"type": "node", "id": 3567225588, "lat": 56.8071292, "lon": 8.4091049}, {"type": "node", "id": 3567225589, "lat": 56.8072287, "lon": 8.4093523}, {"type": "node", "id": 3567225590, "lat": 56.8073794, "lon": 8.40981}, {"type": "node", "id": 3567225591, "lat": 56.8074557, "lon": 8.4101035}, {"type": "node", "id": 3567225592, "lat": 56.8076611, "lon": 8.4110532}, {"type": "node", "id": 3567225597, "lat": 56.8086311, "lon": 8.4165961}, {"type": "node", "id": 3567225598, "lat": 56.8088803, "lon": 8.4178436}, {"type": "node", "id": 3567225599, "lat": 56.8090883, "lon": 8.4186661}, {"type": "node", "id": 3567225600, "lat": 56.8092043, "lon": 8.4190644}, {"type": "node", "id": 3567225604, "lat": 56.8491421, "lon": 8.4892116}, {"type": "node", "id": 3567225614, "lat": 56.8528302, "lon": 8.4920193}, {"type": "node", "id": 3569588001, "lat": 56.7477723, "lon": 8.4174748}, {"type": "node", "id": 3569588002, "lat": 56.7487058, "lon": 8.4174143}, {"type": "node", "id": 3569588003, "lat": 56.7494382, "lon": 8.4175032}, {"type": "node", "id": 3569588004, "lat": 56.7497546, "lon": 8.4175854}, {"type": "node", "id": 3569588005, "lat": 56.7507476, "lon": 8.4178766}, {"type": "node", "id": 3569588006, "lat": 56.7507704, "lon": 8.4179334}, {"type": "node", "id": 3569588007, "lat": 56.7508924, "lon": 8.4179216}, {"type": "node", "id": 3569588008, "lat": 56.7509292, "lon": 8.4180163}, {"type": "node", "id": 3569588009, "lat": 56.7515587, "lon": 8.4182281}, {"type": "node", "id": 3569588010, "lat": 56.7517062, "lon": 8.4181652}, {"type": "node", "id": 3569588011, "lat": 56.752019, "lon": 8.4183618}, {"type": "node", "id": 3569588012, "lat": 56.7522168, "lon": 8.418317}, {"type": "node", "id": 3569588013, "lat": 56.7524698, "lon": 8.4183936}, {"type": "node", "id": 3569588014, "lat": 56.7524822, "lon": 8.418487}, {"type": "node", "id": 3569588015, "lat": 56.7527805, "lon": 8.4185614, "tags": {"railway": "switch", "railway:position:exact": "39.68", "railway:switch:local_operated": "yes", "ref": "SN004"}}, {"type": "node", "id": 3569588016, "lat": 56.7531181, "lon": 8.4186255}, {"type": "node", "id": 3569588017, "lat": 56.7537649, "lon": 8.4187814}, {"type": "node", "id": 3569588019, "lat": 56.755336, "lon": 8.4192523}, {"type": "node", "id": 3569588020, "lat": 56.7580288, "lon": 8.4200581}, {"type": "node", "id": 3714228428, "lat": 56.6786772, "lon": 8.3972317}, {"type": "node", "id": 3903720233, "lat": 56.6824284, "lon": 8.3944188}, {"type": "node", "id": 3903720235, "lat": 56.6832054, "lon": 8.3942748}, {"type": "node", "id": 3903720236, "lat": 56.6838404, "lon": 8.3943943}, {"type": "node", "id": 3903720238, "lat": 56.6840929, "lon": 8.3945187}, {"type": "node", "id": 3993488019, "lat": 56.8538133, "lon": 8.4928784}, {"type": "node", "id": 3993488020, "lat": 56.8544775, "lon": 8.4937435}, {"type": "node", "id": 4161530315, "lat": 56.6575358, "lon": 8.1951766, "tags": {"railway": "switch"}}, {"type": "node", "id": 4161530319, "lat": 56.6571253, "lon": 8.1949299, "tags": {"crossing:barrier": "half", "crossing:bell": "yes", "crossing:light": "yes", "railway": "level_crossing", "ref": "85N"}}, {"type": "node", "id": 4161530321, "lat": 56.6572217, "lon": 8.1949801}, {"type": "node", "id": 4161530329, "lat": 56.6570654, "lon": 8.194897}, {"type": "node", "id": 4161530330, "lat": 56.6569371, "lon": 8.1948219}, {"type": "node", "id": 4161530333, "lat": 56.6549291, "lon": 8.1939904}, {"type": "node", "id": 4161530336, "lat": 56.6573912, "lon": 8.1950793}, {"type": "node", "id": 4161530338, "lat": 56.655053, "lon": 8.1940386}, {"type": "node", "id": 4161530341, "lat": 56.655942, "lon": 8.1944168}, {"type": "node", "id": 4161530343, "lat": 56.6568236, "lon": 8.1947602}, {"type": "node", "id": 4161530344, "lat": 56.6553379, "lon": 8.1941587}, {"type": "node", "id": 4161530346, "lat": 56.6560983, "lon": 8.1944812}, {"type": "node", "id": 4161530350, "lat": 56.6567499, "lon": 8.1947146}, {"type": "node", "id": 4161530355, "lat": 56.6565494, "lon": 8.1946314}, {"type": "node", "id": 4161530358, "lat": 56.6566261, "lon": 8.1946636, "tags": {"name": "R\u00f8nland", "public_transport": "stop_position", "railway": "stop", "train": "yes"}}, {"type": "node", "id": 4161530364, "lat": 56.6545983, "lon": 8.1939217, "tags": {"railway": "switch"}}, {"type": "node", "id": 4161554519, "lat": 56.7045478, "lon": 8.2160134, "tags": {"railway": "switch"}}, {"type": "node", "id": 4161554521, "lat": 56.7049544, "lon": 8.2169859}, {"type": "node", "id": 4161554548, "lat": 56.7048358, "lon": 8.2167217}, {"type": "node", "id": 4161554549, "lat": 56.7047519, "lon": 8.2166949}, {"type": "node", "id": 4161554556, "lat": 56.7048359, "lon": 8.216943}, {"type": "node", "id": 4161554562, "lat": 56.7053092, "lon": 8.2181969}, {"type": "node", "id": 4161554567, "lat": 56.7050633, "lon": 8.2172769}, {"type": "node", "id": 4161554570, "lat": 56.7055109, "lon": 8.2186243, "tags": {"railway": "switch"}}, {"type": "node", "id": 4161554572, "lat": 56.7046761, "lon": 8.2163639, "tags": {"railway": "switch"}}, {"type": "node", "id": 4161554573, "lat": 56.7046731, "lon": 8.2164427}, {"type": "node", "id": 4161555398, "lat": 56.7057476, "lon": 8.2191252, "tags": {"railway": "buffer_stop"}}, {"type": "node", "id": 4161555400, "lat": 56.7053997, "lon": 8.2183967}, {"type": "node", "id": 4161729823, "lat": 56.7052217, "lon": 8.2179734, "tags": {"crossing:barrier": "no", "crossing:bell": "no", "crossing:light": "no", "railway": "crossing"}}, {"type": "node", "id": 4161729826, "lat": 56.7052954, "lon": 8.2179006, "tags": {"crossing:barrier": "no", "crossing:bell": "no", "crossing:light": "no", "railway": "crossing"}}, {"type": "node", "id": 4384223147, "lat": 56.6567574, "lon": 8.4780292}, {"type": "node", "id": 4394410973, "lat": 56.6572333, "lon": 8.1954555}, {"type": "node", "id": 4446868116, "lat": 56.8060738, "lon": 8.4066745, "tags": {"crossing:barrier": "double_half", "crossing:bell": "yes", "crossing:light": "yes", "railway": "level_crossing", "railway:position": "46.3", "ref": "135"}}, {"type": "node", "id": 4446868124, "lat": 56.8062451, "lon": 8.4069629}, {"type": "node", "id": 4446868125, "lat": 56.8062646, "lon": 8.4071313}, {"type": "node", "id": 4446868135, "lat": 56.8063897, "lon": 8.4072298}, {"type": "node", "id": 4446868151, "lat": 56.8065478, "lon": 8.4075465, "tags": {"crossing:barrier": "no", "crossing:bell": "no", "crossing:light": "no", "railway": "crossing"}}, {"type": "node", "id": 4446868171, "lat": 56.8066687, "lon": 8.4078005, "tags": {"name": "Bedsted Thy", "public_transport": "stop_position", "railway": "stop", "train": "yes"}}, {"type": "node", "id": 4446868183, "lat": 56.806911, "lon": 8.4083738}, {"type": "node", "id": 4446868191, "lat": 56.807052, "lon": 8.4087573}, {"type": "node", "id": 4446868198, "lat": 56.8071922, "lon": 8.4091717}, {"type": "node", "id": 4452484717, "lat": 56.8365552, "lon": 8.4721655}, {"type": "node", "id": 4452484723, "lat": 56.8375735, "lon": 8.4741638}, {"type": "node", "id": 4452484734, "lat": 56.8395058, "lon": 8.4809873}, {"type": "node", "id": 4452484739, "lat": 56.8405922, "lon": 8.4826194}, {"type": "node", "id": 4540424610, "lat": 56.702499, "lon": 8.2104899}, {"type": "node", "id": 4540424611, "lat": 56.702305, "lon": 8.2100346}, {"type": "node", "id": 4540424612, "lat": 56.7021323, "lon": 8.2096772}, {"type": "node", "id": 4540424613, "lat": 56.7020455, "lon": 8.2095156}, {"type": "node", "id": 4540424614, "lat": 56.7017038, "lon": 8.208957}, {"type": "node", "id": 4540424615, "lat": 56.7013961, "lon": 8.2085429}, {"type": "node", "id": 4540424616, "lat": 56.7008468, "lon": 8.2080088}, {"type": "node", "id": 4540424617, "lat": 56.699922, "lon": 8.2073232}, {"type": "node", "id": 4540424618, "lat": 56.7001554, "lon": 8.2074821}, {"type": "node", "id": 4540424619, "lat": 56.6994475, "lon": 8.2070821}, {"type": "node", "id": 4540424620, "lat": 56.6987049, "lon": 8.2068987}, {"type": "node", "id": 4540424621, "lat": 56.6939697, "lon": 8.2081165}, {"type": "node", "id": 4540424622, "lat": 56.6932443, "lon": 8.2085533}, {"type": "node", "id": 4540424623, "lat": 56.6928209, "lon": 8.2089436}, {"type": "node", "id": 4540424624, "lat": 56.6923959, "lon": 8.2094385}, {"type": "node", "id": 4540424625, "lat": 56.691658, "lon": 8.2106508}, {"type": "node", "id": 4540424626, "lat": 56.6890155, "lon": 8.2187169}, {"type": "node", "id": 4540424627, "lat": 56.6902897, "lon": 8.2147204}, {"type": "node", "id": 4540424628, "lat": 56.6913347, "lon": 8.2114106}, {"type": "node", "id": 4540424629, "lat": 56.6887117, "lon": 8.2193972}, {"type": "node", "id": 4540424630, "lat": 56.6881696, "lon": 8.2203162}, {"type": "node", "id": 4540424631, "lat": 56.6883574, "lon": 8.2200319}, {"type": "node", "id": 4540424632, "lat": 56.6875384, "lon": 8.2210726}, {"type": "node", "id": 4540424633, "lat": 56.6877226, "lon": 8.2208768}, {"type": "node", "id": 4540424634, "lat": 56.6870597, "lon": 8.2214843}, {"type": "node", "id": 4540424635, "lat": 56.6859349, "lon": 8.2221254}, {"type": "node", "id": 4540424636, "lat": 56.6835602, "lon": 8.2233981}, {"type": "node", "id": 4540424637, "lat": 56.6840765, "lon": 8.2231218}, {"type": "node", "id": 4540424639, "lat": 56.6827322, "lon": 8.2237243}, {"type": "node", "id": 4540424640, "lat": 56.6821211, "lon": 8.2238272}, {"type": "node", "id": 4540424641, "lat": 56.6824283, "lon": 8.2237897}, {"type": "node", "id": 4540424642, "lat": 56.6816092, "lon": 8.2238336}, {"type": "node", "id": 4540424644, "lat": 56.6814062, "lon": 8.2238125}, {"type": "node", "id": 4540424645, "lat": 56.6807384, "lon": 8.2236653}, {"type": "node", "id": 4540424647, "lat": 56.6802217, "lon": 8.2234614}, {"type": "node", "id": 4540424648, "lat": 56.6804769, "lon": 8.2235697}, {"type": "node", "id": 4540424650, "lat": 56.6797428, "lon": 8.2231939}, {"type": "node", "id": 4540424652, "lat": 56.6795174, "lon": 8.2230427}, {"type": "node", "id": 4540424654, "lat": 56.6788087, "lon": 8.2224422}, {"type": "node", "id": 4540424655, "lat": 56.6782878, "lon": 8.2218705}, {"type": "node", "id": 4540424656, "lat": 56.6785457, "lon": 8.2221676}, {"type": "node", "id": 4540424658, "lat": 56.6777421, "lon": 8.2211127}, {"type": "node", "id": 4540424660, "lat": 56.6685114, "lon": 8.2071324}, {"type": "node", "id": 4540424661, "lat": 56.6632185, "lon": 8.1991318}, {"type": "node", "id": 4540424662, "lat": 56.663517, "lon": 8.1995686}, {"type": "node", "id": 4540424663, "lat": 56.6641055, "lon": 8.2004615}, {"type": "node", "id": 4540424666, "lat": 56.6614201, "lon": 8.1971553}, {"type": "node", "id": 4540424668, "lat": 56.6608611, "lon": 8.1967379}, {"type": "node", "id": 4540424683, "lat": 56.6582138, "lon": 8.1954632}, {"type": "node", "id": 4540424687, "lat": 56.6596372, "lon": 8.1980079}, {"type": "node", "id": 4540424688, "lat": 56.6595436, "lon": 8.1980012}, {"type": "node", "id": 4540424689, "lat": 56.6586331, "lon": 8.2010805, "tags": {"railway": "level_crossing"}}, {"type": "node", "id": 4540424690, "lat": 56.658676, "lon": 8.2010888, "tags": {"railway": "level_crossing"}}, {"type": "node", "id": 4540424691, "lat": 56.6599432, "lon": 8.201335, "tags": {"railway": "level_crossing"}}, {"type": "node", "id": 4540424692, "lat": 56.6588982, "lon": 8.1979107}, {"type": "node", "id": 4540424693, "lat": 56.657955, "lon": 8.2011487}, {"type": "node", "id": 4540424694, "lat": 56.6579521, "lon": 8.2010009, "tags": {"railway": "level_crossing"}}, {"type": "node", "id": 4540424695, "lat": 56.6579514, "lon": 8.2008943}, {"type": "node", "id": 4540424696, "lat": 56.6579562, "lon": 8.2007034}, {"type": "node", "id": 4540424697, "lat": 56.6579717, "lon": 8.2004196}, {"type": "node", "id": 4540424698, "lat": 56.6580211, "lon": 8.1995935}, {"type": "node", "id": 4540424699, "lat": 56.6580417, "lon": 8.1993661}, {"type": "node", "id": 4540424700, "lat": 56.658066, "lon": 8.1991784}, {"type": "node", "id": 4540424701, "lat": 56.6581092, "lon": 8.1988733}, {"type": "node", "id": 4540424702, "lat": 56.656699, "lon": 8.1948567}, {"type": "node", "id": 4674463693, "lat": 56.7659355, "lon": 8.4190774}, {"type": "node", "id": 4674463694, "lat": 56.7652481, "lon": 8.419922}, {"type": "node", "id": 4674463695, "lat": 56.7644994, "lon": 8.4205708}, {"type": "node", "id": 4674463696, "lat": 56.7637061, "lon": 8.4210093}, {"type": "node", "id": 4674463697, "lat": 56.762886, "lon": 8.4212278}, {"type": "node", "id": 4674463698, "lat": 56.7624715, "lon": 8.4212528}, {"type": "node", "id": 5100812958, "lat": 56.6750281, "lon": 8.4004057}, {"type": "node", "id": 5100812977, "lat": 56.6801809, "lon": 8.3960514, "tags": {"crossing:barrier": "full", "railway": "level_crossing"}}, {"type": "node", "id": 5679358926, "lat": 56.7318837, "lon": 8.4127767}, {"type": "node", "id": 5679358927, "lat": 56.7313875, "lon": 8.4128311}, {"type": "node", "id": 5679358928, "lat": 56.7309156, "lon": 8.4128009}, {"type": "node", "id": 5679358929, "lat": 56.7304992, "lon": 8.4127124}, {"type": "node", "id": 5679358930, "lat": 56.7300504, "lon": 8.4125521}, {"type": "node", "id": 5679358931, "lat": 56.7295578, "lon": 8.4122986}, {"type": "node", "id": 5679358932, "lat": 56.7293264, "lon": 8.4121571}, {"type": "node", "id": 5679358933, "lat": 56.7288651, "lon": 8.4118681}, {"type": "node", "id": 5679358934, "lat": 56.7279421, "lon": 8.4112864}, {"type": "node", "id": 5679358935, "lat": 56.7260946, "lon": 8.4101334}, {"type": "node", "id": 5987803105, "lat": 56.7139523, "lon": 8.3986257, "tags": {"name": "Ydby", "public_transport": "stop_position", "railway": "stop", "train": "yes"}}, {"type": "node", "id": 5987803152, "lat": 56.6981961, "lon": 8.2069074, "tags": {"name": "Thybor\u00f8n Kirke", "public_transport": "stop_position", "railway": "stop", "train": "yes"}}, {"type": "node", "id": 5987803415, "lat": 56.7511455, "lon": 8.4181132, "tags": {"name": "Hurup Thy", "public_transport": "stop_position", "railway": "stop", "train": "yes"}}, {"type": "node", "id": 5987803416, "lat": 56.7511559, "lon": 8.4180039, "tags": {"name": "Hurup Thy", "public_transport": "stop_position", "railway": "stop", "train": "yes"}}, {"type": "node", "id": 5987803417, "lat": 56.751474, "lon": 8.4180948}, {"type": "node", "id": 5987803423, "lat": 56.8066203, "lon": 8.407873, "tags": {"name": "Bedsted Thy", "public_transport": "stop_position", "railway": "stop", "train": "yes"}}, {"type": "node", "id": 5987803424, "lat": 56.8065021, "lon": 8.4076107}, {"type": "node", "id": 5987803469, "lat": 56.8504984, "lon": 8.4902463, "tags": {"name": "H\u00f8rdum", "public_transport": "stop_position", "railway": "stop", "train": "yes"}}, {"type": "node", "id": 5987803470, "lat": 56.6643128, "lon": 8.4512066, "tags": {"name": "Lyngs", "public_transport": "stop_position", "railway": "stop", "train": "yes"}}, {"type": "node", "id": 6178811921, "lat": 56.7507565, "lon": 8.4180169}, {"type": "node", "id": 6178811922, "lat": 56.7510205, "lon": 8.4181427}, {"type": "node", "id": 6178811923, "lat": 56.7513288, "lon": 8.4182309}, {"type": "node", "id": 6178811924, "lat": 56.7523037, "lon": 8.4185203}, {"type": "node", "id": 6178811925, "lat": 56.7524342, "lon": 8.4185369}, {"type": "node", "id": 6633052785, "lat": 56.8042986, "lon": 8.4047207}, {"type": "node", "id": 6633052786, "lat": 56.8037053, "lon": 8.4043761}, {"type": "node", "id": 6633052787, "lat": 56.803035, "lon": 8.4041494}, {"type": "node", "id": 6812438050, "lat": 56.6553021, "lon": 8.5102388}, {"type": "node", "id": 6812438051, "lat": 56.6558284, "lon": 8.508372}, {"type": "node", "id": 6812438052, "lat": 56.6562987, "lon": 8.5057354}, {"type": "node", "id": 6812438056, "lat": 56.6562235, "lon": 8.5062906}, {"type": "node", "id": 6812438057, "lat": 56.6564491, "lon": 8.5040912}, {"type": "node", "id": 6864004818, "lat": 56.6980176, "lon": 8.4027949}, {"type": "node", "id": 7529060123, "lat": 56.7238825, "lon": 8.4087537}, {"type": "node", "id": 7529066360, "lat": 56.7065098, "lon": 8.4024566}, {"type": "node", "id": 7907707952, "lat": 56.7039232, "lon": 8.2143343}, {"type": "node", "id": 7907707959, "lat": 56.704162, "lon": 8.2149746, "tags": {"name": "Thybor\u00f8n", "public_transport": "stop_position", "railway": "stop", "train": "yes"}}, {"type": "node", "id": 7907708008, "lat": 56.7510902, "lon": 8.4179841, "tags": {"crossing:barrier": "no", "crossing:bell": "no", "crossing:light": "no", "railway": "crossing"}}, {"type": "node", "id": 8693861566, "lat": 56.6566737, "lon": 8.4835338}, {"type": "node", "id": 8693891659, "lat": 56.8389075, "lon": 8.4792472}, {"type": "node", "id": 9866642538, "lat": 56.6893704, "lon": 8.2176826}, {"type": "node", "id": 10801926231, "lat": 56.808396, "lon": 8.4152529}, {"type": "node", "id": 10801926232, "lat": 56.8067361, "lon": 8.4081472}, {"type": "node", "id": 10801926233, "lat": 56.8067855, "lon": 8.4080768}, {"type": "node", "id": 10827931379, "lat": 56.7508353, "lon": 8.4180581, "tags": {"railway": "buffer_stop"}}, {"type": "node", "id": 10858161641, "lat": 56.6345476, "lon": 8.1853277}, {"type": "node", "id": 10876233148, "lat": 56.7007301, "lon": 8.2079177}, {"type": "node", "id": 10876233149, "lat": 56.7032506, "lon": 8.212514}, {"type": "node", "id": 10876233150, "lat": 56.7030804, "lon": 8.2120528}, {"type": "node", "id": 10876233151, "lat": 56.7038116, "lon": 8.2140326}, {"type": "node", "id": 11837844457, "lat": 56.7617521, "lon": 8.4211564}, {"type": "node", "id": 11847272673, "lat": 56.6666985, "lon": 8.4247401}, {"type": "node", "id": 11847272674, "lat": 56.6674222, "lon": 8.4195828}, {"type": "node", "id": 11847272675, "lat": 56.6672763, "lon": 8.4203473}, {"type": "node", "id": 11847272676, "lat": 56.6777592, "lon": 8.3979549}, {"type": "node", "id": 11847272677, "lat": 56.6761833, "lon": 8.3992316}, {"type": "node", "id": 11847272678, "lat": 56.6746574, "lon": 8.4008396}, {"type": "node", "id": 11847272679, "lat": 56.6742883, "lon": 8.4013036}, {"type": "node", "id": 11847272680, "lat": 56.6709799, "lon": 8.4057695}, {"type": "node", "id": 11847272681, "lat": 56.6705128, "lon": 8.4067874}, {"type": "node", "id": 11847272682, "lat": 56.670736, "lon": 8.4062724}, {"type": "node", "id": 11847272683, "lat": 56.6701296, "lon": 8.407875}, {"type": "node", "id": 11847272684, "lat": 56.6699601, "lon": 8.4084705}, {"type": "node", "id": 11847272685, "lat": 56.6715167, "lon": 8.4048977}, {"type": "node", "id": 11847272686, "lat": 56.6718034, "lon": 8.4044968}, {"type": "node", "id": 11847272687, "lat": 56.672387, "lon": 8.4037444}, {"type": "node", "id": 11861178556, "lat": 56.8654255, "lon": 8.5159702}, {"type": "node", "id": 11861178557, "lat": 56.8658556, "lon": 8.5165743}, {"type": "node", "id": 11861178558, "lat": 56.8641545, "lon": 8.5137243}, {"type": "node", "id": 11861178559, "lat": 56.863429, "lon": 8.5122195}, {"type": "node", "id": 11861178560, "lat": 56.8616142, "lon": 8.5084236}, {"type": "node", "id": 11861178561, "lat": 56.867071, "lon": 8.518056}, {"type": "node", "id": 11861178562, "lat": 56.8674803, "lon": 8.5184521}, {"type": "node", "id": 13083958673, "lat": 56.6229037, "lon": 8.1803578}, {"type": "node", "id": 13083958674, "lat": 56.6569514, "lon": 8.1948303, "tags": {"crossing:barrier": "no", "crossing:bell": "no", "crossing:light": "no", "railway": "crossing"}}, {"type": "node", "id": 13083958675, "lat": 56.6920725, "lon": 8.2099021}, {"type": "node", "id": 13087543382, "lat": 56.6579005, "lon": 8.2025655}, {"type": "node", "id": 13087543384, "lat": 56.6579552, "lon": 8.2013826}, {"type": "node", "id": 13087543385, "lat": 56.657954, "lon": 8.2017095, "tags": {"railway": "switch"}}, {"type": "node", "id": 13087543386, "lat": 56.6602279, "lon": 8.2021196}, {"type": "node", "id": 13103695242, "lat": 56.8064149, "lon": 8.4072803, "tags": {"crossing:barrier": "no", "crossing:bell": "yes", "crossing:light": "yes", "railway": "crossing"}}, {"type": "node", "id": 13159244103, "lat": 56.6374434, "lon": 8.1865807}, {"type": "node", "id": 13159244105, "lat": 56.6429865, "lon": 8.188946}, {"type": "way", "id": 25575666, "nodes": [278787353, 277194900], "tags": {"axle_load": "18", "bridge": "yes", "electrified": "no", "gauge": "1435", "layer": "1", "loading_gauge": "TSI_GB", "maxspeed": "75", "metre_load": "6.4", "name": "Thybanen", "operator": "Banedanmark", "operator:wikidata": "Q806420", "operator:wikipedia": "da:Banedanmark", "passenger_lines": "1", "railway": "rail", "railway:bidirectional": "regular", "railway:etcs": "2", "railway:etcs:start_date": "2020-04-06", "railway:preferred_direction": "both", "railway:radio": "gsm-r", "railway:traffic_mode": "passenger", "source:railway:etcs": "https://www.railjournal.com/signalling/ertms-launched-on-third-danish-line/", "source:workrules": "https://www.bane.dk/Jernbanevirksomhed/Sikkerhed/Trafikale-regler", "start_date": "1882-04-20", "usage": "branch", "workrules": "DK:ORF"}}, {"type": "way", "id": 25575668, "nodes": [277194900, 3569588020, 277194901, 3569588019], "tags": {"axle_load": "18", "electrified": "no", "gauge": "1435", "loading_gauge": "TSI_GB", "maxspeed": "75", "metre_load": "6.4", "name": "Thybanen", "operator": "Banedanmark", "operator:wikidata": "Q806420", "operator:wikipedia": "da:Banedanmark", "passenger_lines": "1", "railway": "rail", "railway:bidirectional": "regular", "railway:etcs": "2", "railway:etcs:start_date": "2020-04-06", "railway:preferred_direction": "both", "railway:radio": "gsm-r", "railway:traffic_mode": "passenger", "source:railway:etcs": "https://www.railjournal.com/signalling/ertms-launched-on-third-danish-line/", "source:workrules": "https://www.bane.dk/Jernbanevirksomhed/Sikkerhed/Trafikale-regler", "start_date": "1882-04-20", "usage": "branch", "workrules": "DK:ORF"}}, {"type": "way", "id": 61833012, "nodes": [1603932425, 1603932423, 11861178562, 11861178561, 1603932390, 281923664, 11861178557, 11861178556, 281923665, 11861178558, 11861178559, 1603932268, 11861178560, 1603932228, 1603932208, 281923666, 3993488020, 1149046863, 3993488019, 281923667, 3567225614, 1603932190, 5987803469, 770393526, 3567225604, 322717135, 281923536, 4452484739, 281923668, 1149046871, 4452484734, 1149046861, 8693891659, 1149046847, 1149046865, 4452484723, 1149046890, 1149046860, 4452484717, 281923669, 281923671, 1583590614, 2427958785, 2427958782, 1609983473, 2427958780, 1609983471, 2427958778, 281923541, 2427958775, 1239634436, 2427958772, 2427958756, 281923544, 2427958752, 1609983462, 1609983460, 281923545, 1896162067, 1609983447, 325274746, 1609983441, 3567225600, 3567225599, 1609983438, 3567225598, 1609983435, 3567225597, 10801926231], "tags": {"axle_load": "18", "electrified": "no", "gauge": "1435", "loading_gauge": "TSI_GB", "maxspeed": "75", "metre_load": "6.4", "name": "Thybanen", "operator": "Banedanmark", "operator:wikidata": "Q806420", "operator:wikipedia": "da:Banedanmark", "passenger_lines": "1", "railway": "rail", "railway:bidirectional": "regular", "railway:etcs": "2", "railway:etcs:start_date": "2020-04-06", "railway:preferred_direction": "both", "railway:radio": "gsm-r", "railway:track_ref": "1", "railway:traffic_mode": "passenger", "source:railway:etcs": "https://www.railjournal.com/signalling/ertms-launched-on-third-danish-line/", "source:workrules": "https://www.bane.dk/Jernbanevirksomhed/Sikkerhed/Trafikale-regler", "start_date": "1882-04-20", "usage": "branch", "workrules": "DK:ORF"}}, {"type": "way", "id": 102844894, "nodes": [1187625460, 277193668], "tags": {"axle_load": "18", "bridge": "yes", "electrified": "no", "gauge": "1435", "layer": "1", "loading_gauge": "TSI_GB", "maxspeed": "75", "metre_load": "6.4", "name": "Thybanen", "operator": "Banedanmark", "operator:wikidata": "Q806420", "operator:wikipedia": "da:Banedanmark", "passenger_lines": "1", "railway": "rail", "railway:bidirectional": "regular", "railway:etcs": "2", "railway:etcs:start_date": "2020-04-06", "railway:preferred_direction": "both", "railway:radio": "gsm-r", "railway:traffic_mode": "passenger", "source:railway:etcs": "https://www.railjournal.com/signalling/ertms-launched-on-third-danish-line/", "source:workrules": "https://www.bane.dk/Jernbanevirksomhed/Sikkerhed/Trafikale-regler", "start_date": "1882-04-20", "usage": "branch", "workrules": "DK:ORF"}}, {"type": "way", "id": 102844908, "nodes": [1187625486, 3569588012, 3569588013, 1187625467, 1187624356, 2211757253], "tags": {"axle_load": "18", "electrified": "no", "gauge": "1435", "loading_gauge": "TSI_GB", "maxspeed": "75", "metre_load": "6.4", "name": "Thybanen", "operator": "Banedanmark", "operator:wikidata": "Q806420", "operator:wikipedia": "da:Banedanmark", "passenger_lines": "1", "railway": "rail", "railway:bidirectional": "regular", "railway:etcs": "2", "railway:etcs:start_date": "2020-04-06", "railway:preferred_direction": "both", "railway:radio": "gsm-r", "railway:track_ref": "1", "railway:traffic_mode": "passenger", "source:railway:etcs": "https://www.railjournal.com/signalling/ertms-launched-on-third-danish-line/", "source:workrules": "https://www.bane.dk/Jernbanevirksomhed/Sikkerhed/Trafikale-regler", "start_date": "1882-04-20", "usage": "branch", "workrules": "DK:ORF"}}, {"type": "way", "id": 126081607, "nodes": [499503602, 4540424619, 1165238934, 499503604, 4540424620, 935084528, 5987803152, 935084536, 935084539, 499503609, 1165239074, 1165238933, 1165239142, 4540424621, 499503612, 1165239153, 4540424622, 499503614, 4540424623, 1165238963, 4540424624, 499503616, 13083958675, 1165239594, 1165239084, 4540424625, 499503617, 4540424628, 1165239003, 499503619, 4540424627, 1165239506, 1165239431, 9866642538, 1165239010, 4540424626, 499503621, 4540424629, 1165239352, 4540424631, 4540424630, 499503623, 4540424633, 4540424632, 499503624, 4540424634, 499503626, 4540424635, 499503628, 4540424637, 4540424636, 499503629, 4540424639, 4540424641, 4540424640, 499503631, 4540424642, 4540424644, 499503634, 4540424645, 4540424648, 4540424647, 499503635, 4540424650, 4540424652, 499503638, 4540424654, 4540424656, 4540424655, 499503640, 4540424658, 1530337679, 499503641, 4540424660, 499503644, 4540424663, 4540424662, 4540424661, 499503647, 1458086028, 1458086026, 1458086024, 4540424666, 499503648, 4540424668, 499503650, 1458086017, 1458086011, 1458085989, 4540424683, 4161530315, 1458085956, 499503652, 1458085940, 4161530364, 13159244105, 499503654, 13159244103, 10858161641, 1402454803, 13083958673], "tags": {"alt_name": "Lemvigbanen;VLTJ", "axle_load": "22.5", "electrified": "no", "gauge": "1435", "loading_gauge": "TSI_GB", "maxspeed": "75", "name": "Vemb-Lemvig-Thybor\u00f8n Jernbane", "operator": "Midtjyske Jernbaner A/S", "operator:wikidata": "Q2144315", "operator:wikipedia": "da:Midtjyske_Jernbaner", "passenger_lines": "1", "railway": "rail", "railway:bidirectional": "regular", "railway:etcs": "no", "railway:preferred_direction": "both", "railway:radio": "gsm-r", "railway:traffic_mode": "passenger", "start_date": "1957", "usage": "branch"}}, {"type": "way", "id": 132569500, "nodes": [1458086010, 4540424687, 4540424688, 1458085994], "tags": {"electrified": "no", "gauge": "1435", "maxspeed": "15", "railway": "rail", "railway:etcs": "no", "service": "spur", "usage": "industrial"}}, {"type": "way", "id": 132569502, "nodes": [1458085940, 4540424702, 1458085945, 1458085949, 1458085957, 4394410973, 1458085963, 1529929238, 1458085965, 1458085975, 1458085977, 2628292675, 2628292682, 1458085981, 1458085990, 1458085996, 2628606479, 1458086000, 1458086004, 4540424691, 1458086012, 1458086013, 13087543386, 2628606533, 1458086016, 1458086019, 1458086020, 1458086018, 2628606536, 2628606526, 1458086014, 2628606520, 2628292717, 2628292709, 2628292701], "tags": {"electrified": "no", "fixme": "Who is the owner or operator? Cheminova or Midtjyske Jernbaner?", "gauge": "1435", "maxspeed": "15", "railway": "rail", "railway:etcs": "no", "service": "spur", "usage": "industrial"}}, {"type": "way", "id": 132569503, "nodes": [1458085977, 2628292674, 2628292680, 1458085980, 1458085984, 1458085986, 1458085987, 1458085985, 2628292687, 4540424690, 1458085982], "tags": {"electrified": "no", "gauge": "1435", "maxspeed": "15", "railway": "rail", "railway:etcs": "no", "service": "spur", "usage": "industrial"}}, {"type": "way", "id": 132569504, "nodes": [13087543382, 13087543385, 2628606438, 1458085971, 1458085973, 1458085972, 1458085970, 1458085969, 1458085967, 1458085965], "tags": {"electrified": "no", "gauge": "1435", "maxspeed": "15", "railway": "rail", "railway:etcs": "no", "service": "spur", "usage": "industrial"}}, {"type": "way", "id": 132569505, "nodes": [1458085975, 2628292672, 1458085978, 1458085988, 4540424692, 1458085992, 1458085994, 1458085995, 1458086009], "tags": {"electrified": "no", "gauge": "1435", "maxspeed": "15", "railway": "rail", "railway:etcs": "no", "service": "spur", "usage": "industrial"}}, {"type": "way", "id": 257231807, "nodes": [2628292709, 2628292707, 2628292705, 2628292704, 2628292706, 2628292710, 2628292712, 2628292714, 2628292715, 2628292717], "tags": {"electrified": "no", "gauge": "1435", "maxspeed": "15", "railway": "rail", "railway:etcs": "no", "service": "spur", "usage": "industrial"}}, {"type": "way", "id": 257231808, "nodes": [2628292705, 2628292714], "tags": {"electrified": "no", "gauge": "1435", "maxspeed": "15", "railway": "rail", "railway:etcs": "no", "service": "spur", "usage": "industrial"}}, {"type": "way", "id": 257231809, "nodes": [1458086020, 2628292728], "tags": {"electrified": "no", "gauge": "1435", "maxspeed": "15", "railway": "rail", "railway:etcs": "no", "service": "spur", "usage": "industrial"}}, {"type": "way", "id": 257231811, "nodes": [2628292715, 2628292707], "tags": {"electrified": "no", "gauge": "1435", "maxspeed": "15", "railway": "rail", "railway:etcs": "no", "service": "spur", "usage": "industrial"}}, {"type": "way", "id": 257231812, "nodes": [2628292677, 4540424689, 2628292684, 2628292685, 2628292687], "tags": {"electrified": "no", "gauge": "1435", "maxspeed": "15", "railway": "rail", "railway:etcs": "no", "service": "spur", "usage": "industrial"}}, {"type": "way", "id": 257231814, "nodes": [1458086014, 2628292719, 2628292721, 2628606530, 2628292724, 2628606544, 2628292726, 1458086018], "tags": {"electrified": "no", "gauge": "1435", "maxspeed": "15", "railway": "rail", "railway:etcs": "no", "service": "spur", "usage": "industrial"}}, {"type": "way", "id": 257231815, "nodes": [1458086000, 2628292699, 2628606481, 2628292698, 2628292696, 2628292694, 2628292692, 2628292690, 2628292672], "tags": {"electrified": "no", "gauge": "1435", "maxspeed": "15", "railway": "rail", "railway:etcs": "no", "service": "spur", "usage": "industrial"}}, {"type": "way", "id": 298135527, "nodes": [3020386173, 3020386174], "tags": {"axle_load": "18", "bridge": "yes", "electrified": "no", "gauge": "1435", "layer": "1", "loading_gauge": "TSI_GB", "maxspeed": "75", "metre_load": "6.4", "name": "Thybanen", "operator": "Banedanmark", "operator:wikidata": "Q806420", "operator:wikipedia": "da:Banedanmark", "passenger_lines": "1", "railway": "rail", "railway:bidirectional": "regular", "railway:etcs": "2", "railway:etcs:start_date": "2020-04-06", "railway:preferred_direction": "both", "railway:radio": "gsm-r", "railway:traffic_mode": "passenger", "source:railway:etcs": "https://www.railjournal.com/signalling/ertms-launched-on-third-danish-line/", "source:workrules": "https://www.bane.dk/Jernbanevirksomhed/Sikkerhed/Trafikale-regler", "start_date": "1882-04-20", "usage": "branch", "workrules": "DK:ORF"}}, {"type": "way", "id": 298135528, "nodes": [3020386174, 11847272673, 1227976591, 277193325, 11847272675, 11847272674, 277193326, 277193327, 11847272684, 11847272683, 1227976517, 11847272681, 11847272682, 11847272680, 277193328, 11847272685, 11847272686, 11847272687, 277193329, 11847272679, 11847272678, 5100812958, 608662604, 11847272677, 277193330, 11847272676, 3714228428, 5100812977, 1187625281, 277193331, 3903720233, 277193442, 3903720235, 277193441, 3903720236, 3903720238, 1518673645, 277193439, 2838660840, 1837614484, 1837614527, 277193438, 1837614884, 277193437, 2838660841, 2838660842, 277193436, 2838660843, 1187625101, 2838660844, 277193435, 1187624115, 2838660845, 277193434, 6864004818, 277193433, 2838660846, 2838660847, 2838660848, 2838660849, 277193666, 2838660850, 277193667, 1187625460], "tags": {"axle_load": "18", "electrified": "no", "gauge": "1435", "loading_gauge": "TSI_GB", "maxspeed": "75", "metre_load": "6.4", "name": "Thybanen", "operator": "Banedanmark", "operator:wikidata": "Q806420", "operator:wikipedia": "da:Banedanmark", "passenger_lines": "1", "railway": "rail", "railway:bidirectional": "regular", "railway:etcs": "2", "railway:etcs:start_date": "2020-04-06", "railway:preferred_direction": "both", "railway:radio": "gsm-r", "railway:traffic_mode": "passenger", "source:railway:etcs": "https://www.railjournal.com/signalling/ertms-launched-on-third-danish-line/", "source:workrules": "https://www.bane.dk/Jernbanevirksomhed/Sikkerhed/Trafikale-regler", "start_date": "1882-04-20", "usage": "branch", "workrules": "DK:ORF"}}, {"type": "way", "id": 415077170, "nodes": [4161530315, 4161530336, 4161530321, 4161530319, 4161530329, 13083958674, 4161530330, 4161530343, 4161530350, 4161530358, 4161530355, 4161530346, 4161530341, 4161530344, 4161530338, 4161530333, 4161530364], "tags": {"alt_name": "Lemvigbanen;VLTJ", "axle_load": "22.5", "electrified": "no", "gauge": "1435", "loading_gauge": "TSI_GB", "maxspeed": "40", "name": "Vemb-Lemvig-Thybor\u00f8n Jernbane", "operator": "Midtjyske Jernbaner A/S", "operator:wikidata": "Q2144315", "operator:wikipedia": "da:Midtjyske_Jernbaner", "passenger_lines": "1", "railway": "rail", "railway:bidirectional": "regular", "railway:etcs": "no", "railway:preferred_direction": "both", "railway:traffic_mode": "passenger", "service": "siding", "start_date": "1957"}}, {"type": "way", "id": 415080870, "nodes": [4161554519, 4161554573, 4161554549, 4161554556, 4161729823, 4161554562, 4161555400, 4161554570], "tags": {"electrified": "no", "gauge": "1435", "operator": "Midtjyske Jernbaner A/S", "operator:wikidata": "Q2144315", "operator:wikipedia": "da:Midtjyske_Jernbaner", "passenger_lines": "1", "railway": "rail", "railway:bidirectional": "regular", "railway:etcs": "no", "railway:preferred_direction": "both", "service": "yard"}}, {"type": "way", "id": 415080879, "nodes": [4161554572, 4161554548, 4161554521, 4161554567, 4161729826, 4161555398], "tags": {"electrified": "no", "gauge": "1435", "operator": "Midtjyske Jernbaner A/S", "operator:wikidata": "Q2144315", "operator:wikipedia": "da:Midtjyske_Jernbaner", "passenger_lines": "1", "railway": "rail", "railway:bidirectional": "regular", "railway:etcs": "no", "railway:preferred_direction": "both", "service": "yard"}}, {"type": "way", "id": 447597499, "nodes": [4446868135, 4446868124, 4446868116, 1609983417], "tags": {"axle_load": "18", "electrified": "no", "gauge": "1435", "loading_gauge": "TSI_GB", "maxspeed": "75", "metre_load": "6.4", "name": "Thybanen", "operator": "Banedanmark", "operator:wikidata": "Q806420", "operator:wikipedia": "da:Banedanmark", "passenger_lines": "1", "railway": "rail", "railway:bidirectional": "regular", "railway:etcs": "2", "railway:etcs:start_date": "2020-04-06", "railway:preferred_direction": "both", "railway:radio": "gsm-r", "railway:track_ref": "1", "railway:traffic_mode": "passenger", "source:railway:etcs": "https://www.railjournal.com/signalling/ertms-launched-on-third-danish-line/", "source:workrules": "https://www.bane.dk/Jernbanevirksomhed/Sikkerhed/Trafikale-regler", "start_date": "1882-04-20", "usage": "branch", "workrules": "DK:ORF"}}, {"type": "way", "id": 457985869, "nodes": [1458085971, 4540424701, 4540424700, 4540424699, 4540424698, 4540424697, 4540424696, 4540424695, 4540424694, 4540424693, 13087543384, 13087543385], "tags": {"electrified": "no", "gauge": "1435", "railway": "rail", "railway:etcs": "no", "service": "spur", "usage": "industrial"}}, {"type": "way", "id": 659942495, "nodes": [1609983417, 3567225585, 3567225584, 1609983416, 3567225583, 3567225582, 1609983414, 6633052785, 1609983413, 6633052786, 1609983412, 6633052787, 1609983409, 2427958732, 1609983402, 1609983400, 1609983399, 1609983398, 1609983397, 2427958712, 1609983396, 1609983395, 1609983394, 2427958710, 1465969461, 1609983388, 2427958705, 277195416, 2427958699, 1586181478, 1586181477, 2427958692, 277194529, 277194530, 277194531, 2427958686, 1578613661, 2427958684, 277194532, 2427958680, 277194534, 4674463693, 1882173155, 4674463694, 1586181397, 4674463695, 1586181389, 4674463696, 277194535, 4674463697, 4674463698, 1586181375, 11837844457, 277194899, 278787353], "tags": {"axle_load": "18", "electrified": "no", "gauge": "1435", "loading_gauge": "TSI_GB", "maxspeed": "75", "metre_load": "6.4", "name": "Thybanen", "operator": "Banedanmark", "operator:wikidata": "Q806420", "operator:wikipedia": "da:Banedanmark", "passenger_lines": "1", "railway": "rail", "railway:bidirectional": "regular", "railway:etcs": "2", "railway:etcs:start_date": "2020-04-06", "railway:preferred_direction": "both", "railway:radio": "gsm-r", "railway:traffic_mode": "passenger", "source:railway:etcs": "https://www.railjournal.com/signalling/ertms-launched-on-third-danish-line/", "source:workrules": "https://www.bane.dk/Jernbanevirksomhed/Sikkerhed/Trafikale-regler", "start_date": "1882-04-20", "usage": "branch", "workrules": "DK:ORF"}}, {"type": "way", "id": 659942499, "nodes": [10801926232, 5987803423, 5987803424, 4446868125, 1906788141, 1609983417], "tags": {"axle_load": "18", "electrified": "no", "gauge": "1435", "loading_gauge": "TSI_GB", "maxspeed": "50", "metre_load": "6.4", "operator": "Banedanmark", "operator:wikidata": "Q806420", "operator:wikipedia": "da:Banedanmark", "passenger_lines": "1", "railway": "rail", "railway:bidirectional": "regular", "railway:etcs": "2", "railway:etcs:start_date": "2020-04-06", "railway:preferred_direction": "both", "railway:radio": "gsm-r", "railway:track_ref": "2", "railway:traffic_mode": "passenger", "service": "siding", "source:railway:etcs": "https://www.railjournal.com/signalling/ertms-launched-on-third-danish-line/", "source:workrules": "https://www.bane.dk/Jernbanevirksomhed/Sikkerhed/Trafikale-regler", "workrules": "DK:ORF"}}, {"type": "way", "id": 659944105, "nodes": [1187625093, 1187624626, 3569588004, 3569588003, 277194902, 3569588002, 277194903, 3569588001, 277194904, 277194905, 2838660899, 277194373, 2838660897, 2838660896, 1187623824, 277194543, 1187624004, 325278725, 325278724, 325278723, 277194542, 325278722, 277194540, 325278721, 277194539, 5679358926, 325278720, 5679358927, 325278719, 5679358928, 277194422, 5679358929, 325278718, 5679358930, 325278717, 5679358931, 5679358932, 5679358933, 5679358934, 5679358935, 7529060123, 1586181145, 2838660881, 277193939, 2838660880, 1586181143, 277193938, 2838660874, 1586181141, 2838660872, 277193937, 1586181117, 2838660869, 277193936, 5987803105, 277193673, 2838660860, 277193672, 2838660859, 608662649, 2838660858, 2838660857, 2838660856, 277193671, 277193670, 7529066360, 2838660853, 277193669, 2838660852, 2838660851, 277193668], "tags": {"axle_load": "18", "electrified": "no", "gauge": "1435", "loading_gauge": "TSI_GB", "maxspeed": "75", "metre_load": "6.4", "name": "Thybanen", "operator": "Banedanmark", "operator:wikidata": "Q806420", "operator:wikipedia": "da:Banedanmark", "passenger_lines": "1", "railway": "rail", "railway:bidirectional": "regular", "railway:etcs": "2", "railway:etcs:start_date": "2020-04-06", "railway:preferred_direction": "both", "railway:radio": "gsm-r", "railway:traffic_mode": "passenger", "source:railway:etcs": "https://www.railjournal.com/signalling/ertms-launched-on-third-danish-line/", "source:workrules": "https://www.bane.dk/Jernbanevirksomhed/Sikkerhed/Trafikale-regler", "start_date": "1882-04-20", "usage": "branch", "workrules": "DK:ORF"}}, {"type": "way", "id": 659944106, "nodes": [2211757253, 3569588016, 1187624909, 3569588015, 3569588014, 3569588011, 3569588009, 5987803415, 1586181210], "tags": {"axle_load": "18", "electrified": "no", "gauge": "1435", "loading_gauge": "TSI_GB", "maxspeed": "75", "metre_load": "6.4", "operator": "Banedanmark", "operator:wikidata": "Q806420", "operator:wikipedia": "da:Banedanmark", "passenger_lines": "1", "railway": "rail", "railway:bidirectional": "regular", "railway:etcs": "2", "railway:etcs:start_date": "2020-04-06", "railway:preferred_direction": "both", "railway:radio": "gsm-r", "railway:track_ref": "2", "railway:traffic_mode": "passenger", "service": "siding", "source:railway:etcs": "https://www.railjournal.com/signalling/ertms-launched-on-third-danish-line/", "source:workrules": "https://www.bane.dk/Jernbanevirksomhed/Sikkerhed/Trafikale-regler", "workrules": "DK:ORF"}}, {"type": "way", "id": 659944107, "nodes": [6178811921, 10827931379, 6178811922, 6178811923, 6178811924, 6178811925, 3569588015], "tags": {"electrified": "no", "gauge": "1435", "operator": "Banedanmark", "operator:wikidata": "Q806420", "operator:wikipedia": "da:Banedanmark", "railway": "rail", "railway:etcs": "no", "service": "yard", "workrules": "DK:ORF"}}, {"type": "way", "id": 847410900, "nodes": [499503593, 4161554570, 2371627104, 4161554572, 4161554519, 935084469, 1165239414, 7907707959], "tags": {"alt_name": "Lemvigbanen;VLTJ", "electrified": "no", "gauge": "1435", "name": "Vemb-Lemvig-Thybor\u00f8n Jernbane", "operator": "Midtjyske Jernbaner A/S", "operator:wikidata": "Q2144315", "operator:wikipedia": "da:Midtjyske_Jernbaner", "passenger_lines": "1", "railway": "rail", "railway:bidirectional": "regular", "railway:etcs": "no", "railway:preferred_direction": "both", "railway:track_ref": "1", "service": "yard"}}, {"type": "way", "id": 1161369115, "nodes": [608662673, 277192953, 277192952, 6812438050, 858835505, 6812438051, 608662671, 6812438056, 6812438052, 858835508, 6812438057, 277192951, 1302252871, 277192950, 1974924291, 1302253144, 8693861566, 277192990, 4384223147, 277192991, 1974924290, 1974931692, 277192992, 1302252677, 277192994, 1974931689, 277192995, 277192996, 1974931686, 277192997, 1227979886, 5987803470, 277192998, 277192999, 3020386173], "tags": {"axle_load": "18", "electrified": "no", "gauge": "1435", "loading_gauge": "TSI_GB", "maxspeed": "75", "metre_load": "6.4", "name": "Thybanen", "operator": "Banedanmark", "operator:wikidata": "Q806420", "operator:wikipedia": "da:Banedanmark", "passenger_lines": "1", "railway": "rail", "railway:bidirectional": "regular", "railway:etcs": "2", "railway:etcs:start_date": "2020-04-06", "railway:preferred_direction": "both", "railway:radio": "gsm-r", "railway:traffic_mode": "passenger", "source:railway:etcs": "https://www.railjournal.com/signalling/ertms-launched-on-third-danish-line/", "source:workrules": "https://www.bane.dk/Jernbanevirksomhed/Sikkerhed/Trafikale-regler", "start_date": "1882-04-20", "usage": "branch", "workrules": "DK:ORF"}}, {"type": "way", "id": 1161369116, "nodes": [1586181210, 3569588008, 3569588006, 1187625093], "tags": {"electrified": "no", "gauge": "1435", "maxspeed": "75", "name": "Thybanen", "operator": "Banedanmark", "operator:wikidata": "Q806420", "operator:wikipedia": "da:Banedanmark", "passenger_lines": "1", "railway": "rail", "railway:etcs": "2", "railway:etcs:start_date": "2020-04", "railway:track_ref": "2", "service": "siding", "source:railway:etcs": "https://www.railjournal.com/signalling/ertms-launched-on-third-danish-line/", "source:workrules": "https://www.bane.dk/Jernbanevirksomhed/Sikkerhed/Trafikale-regler", "tracks": "1", "workrules": "DK:ORF"}}, {"type": "way", "id": 1161369117, "nodes": [1187625093, 3569588005, 3569588007, 7907708008], "tags": {"axle_load": "18", "electrified": "no", "gauge": "1435", "loading_gauge": "TSI_GB", "maxspeed": "75", "metre_load": "6.4", "name": "Thybanen", "operator": "Banedanmark", "operator:wikidata": "Q806420", "operator:wikipedia": "da:Banedanmark", "passenger_lines": "1", "railway": "rail", "railway:bidirectional": "regular", "railway:etcs": "2", "railway:etcs:start_date": "2020-04-06", "railway:preferred_direction": "both", "railway:radio": "gsm-r", "railway:track_ref": "1", "railway:traffic_mode": "passenger", "source:railway:etcs": "https://www.railjournal.com/signalling/ertms-launched-on-third-danish-line/", "source:workrules": "https://www.bane.dk/Jernbanevirksomhed/Sikkerhed/Trafikale-regler", "start_date": "1882-04-20", "usage": "branch", "workrules": "DK:ORF"}}, {"type": "way", "id": 1161369118, "nodes": [3569588019, 2838661391, 3569588017, 2211757253], "tags": {"axle_load": "18", "electrified": "no", "gauge": "1435", "loading_gauge": "TSI_GB", "maxspeed": "75", "metre_load": "6.4", "name": "Thybanen", "operator": "Banedanmark", "operator:wikidata": "Q806420", "operator:wikipedia": "da:Banedanmark", "passenger_lines": "1", "railway": "rail", "railway:bidirectional": "regular", "railway:etcs": "2", "railway:etcs:start_date": "2020-04-06", "railway:preferred_direction": "both", "railway:radio": "gsm-r", "railway:traffic_mode": "passenger", "source:railway:etcs": "https://www.railjournal.com/signalling/ertms-launched-on-third-danish-line/", "source:workrules": "https://www.bane.dk/Jernbanevirksomhed/Sikkerhed/Trafikale-regler", "start_date": "1882-04-20", "usage": "branch", "workrules": "DK:ORF"}}, {"type": "way", "id": 1161369119, "nodes": [10801926231, 3567225592, 1609983431, 3567225591, 3567225590, 1609983425], "tags": {"axle_load": "18", "electrified": "no", "gauge": "1435", "loading_gauge": "TSI_GB", "maxspeed": "75", "metre_load": "6.4", "name": "Thybanen", "operator": "Banedanmark", "operator:wikidata": "Q806420", "operator:wikipedia": "da:Banedanmark", "passenger_lines": "1", "railway": "rail", "railway:bidirectional": "regular", "railway:etcs": "2", "railway:etcs:start_date": "2020-04-06", "railway:preferred_direction": "both", "railway:radio": "gsm-r", "railway:traffic_mode": "passenger", "source:railway:etcs": "https://www.railjournal.com/signalling/ertms-launched-on-third-danish-line/", "source:workrules": "https://www.bane.dk/Jernbanevirksomhed/Sikkerhed/Trafikale-regler", "start_date": "1882-04-20", "usage": "branch", "workrules": "DK:ORF"}}, {"type": "way", "id": 1161369120, "nodes": [1609983425, 3567225589, 3567225588, 3567225587, 10801926232], "tags": {"axle_load": "18", "electrified": "no", "gauge": "1435", "loading_gauge": "TSI_GB", "maxspeed": "50", "metre_load": "6.4", "operator": "Banedanmark", "operator:wikidata": "Q806420", "operator:wikipedia": "da:Banedanmark", "passenger_lines": "1", "railway": "rail", "railway:bidirectional": "regular", "railway:etcs": "2", "railway:etcs:start_date": "2020-04-06", "railway:preferred_direction": "both", "railway:radio": "gsm-r", "railway:track_ref": "2", "railway:traffic_mode": "passenger", "service": "siding", "source:railway:etcs": "https://www.railjournal.com/signalling/ertms-launched-on-third-danish-line/", "source:workrules": "https://www.bane.dk/Jernbanevirksomhed/Sikkerhed/Trafikale-regler", "workrules": "DK:ORF"}}, {"type": "way", "id": 1161369121, "nodes": [1609983425, 4446868198, 4446868191, 4446868183, 10801926233], "tags": {"axle_load": "18", "electrified": "no", "gauge": "1435", "loading_gauge": "TSI_GB", "maxspeed": "75", "metre_load": "6.4", "name": "Thybanen", "operator": "Banedanmark", "operator:wikidata": "Q806420", "operator:wikipedia": "da:Banedanmark", "passenger_lines": "1", "railway": "rail", "railway:bidirectional": "regular", "railway:etcs": "2", "railway:etcs:start_date": "2020-04-06", "railway:preferred_direction": "both", "railway:radio": "gsm-r", "railway:track_ref": "1", "railway:traffic_mode": "passenger", "source:railway:etcs": "https://www.railjournal.com/signalling/ertms-launched-on-third-danish-line/", "source:workrules": "https://www.bane.dk/Jernbanevirksomhed/Sikkerhed/Trafikale-regler", "start_date": "1882-04-20", "usage": "branch", "workrules": "DK:ORF"}}, {"type": "way", "id": 1169697299, "nodes": [10876233149, 10876233150, 1165239498, 4540424610, 1165239338, 4540424611, 499503595, 4540424612, 4540424613, 1165239039, 4540424614, 499503597, 4540424615, 1165239236, 1165239106, 4540424616, 10876233148], "tags": {"alt_name": "Lemvigbanen;VLTJ", "axle_load": "22.5", "electrified": "no", "gauge": "1435", "loading_gauge": "TSI_GB", "maxspeed:backward": "75", "maxspeed:forward": "50", "name": "Vemb-Lemvig-Thybor\u00f8n Jernbane", "operator": "Midtjyske Jernbaner A/S", "operator:wikidata": "Q2144315", "operator:wikipedia": "da:Midtjyske_Jernbaner", "passenger_lines": "1", "railway": "rail", "railway:bidirectional": "regular", "railway:etcs": "no", "railway:preferred_direction": "both", "railway:radio": "gsm-r", "railway:traffic_mode": "passenger", "start_date": "1899-11-01", "usage": "branch"}}, {"type": "way", "id": 1169697301, "nodes": [10876233151, 935036599, 10876233149], "tags": {"alt_name": "Lemvigbanen;VLTJ", "axle_load": "22.5", "electrified": "no", "gauge": "1435", "loading_gauge": "TSI_GB", "maxspeed": "40", "name": "Vemb-Lemvig-Thybor\u00f8n Jernbane", "operator": "Midtjyske Jernbaner A/S", "operator:wikidata": "Q2144315", "operator:wikipedia": "da:Midtjyske_Jernbaner", "passenger_lines": "1", "railway": "rail", "railway:bidirectional": "regular", "railway:etcs": "no", "railway:preferred_direction": "both", "railway:radio": "gsm-r", "railway:track_ref": "1", "railway:traffic_mode": "passenger", "start_date": "1899-11-01", "usage": "branch"}}, {"type": "way", "id": 1169697302, "nodes": [7907707959, 7907707952, 10876233151], "tags": {"alt_name": "Lemvigbanen;VLTJ", "axle_load": "22.5", "electrified": "no", "gauge": "1435", "loading_gauge": "TSI_GB", "maxspeed": "40", "name": "Vemb-Lemvig-Thybor\u00f8n Jernbane", "operator": "Midtjyske Jernbaner A/S", "operator:wikidata": "Q2144315", "operator:wikipedia": "da:Midtjyske_Jernbaner", "passenger_lines": "1", "railway": "rail", "railway:bidirectional": "regular", "railway:etcs": "no", "railway:preferred_direction": "both", "railway:radio": "gsm-r", "railway:track_ref": "1", "railway:traffic_mode": "passenger", "start_date": "1899-11-01", "usage": "branch"}}, {"type": "way", "id": 1423503370, "nodes": [10876233148, 935084487, 4540424618, 4540424617, 499503602], "tags": {"alt_name": "Lemvigbanen;VLTJ", "axle_load": "22.5", "electrified": "no", "gauge": "1435", "loading_gauge": "TSI_GB", "maxspeed": "75", "name": "Vemb-Lemvig-Thybor\u00f8n Jernbane", "operator": "Midtjyske Jernbaner A/S", "operator:wikidata": "Q2144315", "operator:wikipedia": "da:Midtjyske_Jernbaner", "passenger_lines": "1", "railway": "rail", "railway:bidirectional": "regular", "railway:etcs": "no", "railway:preferred_direction": "both", "railway:radio": "gsm-r", "railway:traffic_mode": "passenger", "start_date": "1899-11-01", "usage": "branch"}}, {"type": "way", "id": 1425577819, "nodes": [10801926233, 4446868171, 4446868151, 13103695242, 4446868135], "tags": {"axle_load": "18", "electrified": "no", "gauge": "1435", "loading_gauge": "TSI_GB", "maxspeed": "50", "metre_load": "6.4", "name": "Thybanen", "operator": "Banedanmark", "operator:wikidata": "Q806420", "operator:wikipedia": "da:Banedanmark", "passenger_lines": "1", "railway": "rail", "railway:bidirectional": "regular", "railway:etcs": "2", "railway:etcs:start_date": "2020-04-06", "railway:preferred_direction": "both", "railway:radio": "gsm-r", "railway:track_ref": "1", "railway:traffic_mode": "passenger", "source:railway:etcs": "https://www.railjournal.com/signalling/ertms-launched-on-third-danish-line/", "source:workrules": "https://www.bane.dk/Jernbanevirksomhed/Sikkerhed/Trafikale-regler", "start_date": "1882-04-20", "usage": "branch", "workrules": "DK:ORF"}}, {"type": "way", "id": 1425577829, "nodes": [7907708008, 5987803416, 5987803417, 3569588010, 1187624606, 1187625486], "tags": {"axle_load": "18", "electrified": "no", "gauge": "1435", "loading_gauge": "TSI_GB", "maxspeed": "50", "metre_load": "6.4", "name": "Thybanen", "operator": "Banedanmark", "operator:wikidata": "Q806420", "operator:wikipedia": "da:Banedanmark", "passenger_lines": "1", "railway": "rail", "railway:bidirectional": "regular", "railway:etcs": "2", "railway:etcs:start_date": "2020-04-06", "railway:preferred_direction": "both", "railway:radio": "gsm-r", "railway:track_ref": "1", "railway:traffic_mode": "passenger", "source:railway:etcs": "https://www.railjournal.com/signalling/ertms-launched-on-third-danish-line/", "source:workrules": "https://www.bane.dk/Jernbanevirksomhed/Sikkerhed/Trafikale-regler", "start_date": "1882-04-20", "usage": "branch", "workrules": "DK:ORF"}}]}